{
  "result" : [ {
    "Rank" : "1",
    "Bib" : "",
    "FIS Code" : "205171",
    "Name" : "SEIZINGER Katja",
    "Year" : "1972",
    "Nation" : "GER",
    "Total Time" : "1:20.93",
    "Diff." : "",
    "FIS Points" : "0.00",
    "WC Points" : "0.00"
  }, {
    "Rank" : "2",
    "Bib" : "",
    "FIS Code" : "55069",
    "Name" : "GOETSCHL Renate",
    "Year" : "1975",
    "Nation" : "AUT",
    "Total Time" : "1:21.13",
    "Diff." : "+0.20",
    "FIS Points" : "2.32",
    "WC Points" : "0.00"
  }, {
    "Rank" : "3",
    "Bib" : "",
    "FIS Code" : "195113",
    "Name" : "MASNADA Florence",
    "Year" : "1968",
    "Nation" : "FRA",
    "Total Time" : "1:21.26",
    "Diff." : "+0.33",
    "FIS Points" : "3.83",
    "WC Points" : "0.00"
  }, {
    "Rank" : "4",
    "Bib" : "",
    "FIS Code" : "205044",
    "Name" : "GERG-LEITNER Michaela",
    "Year" : "1965",
    "Nation" : "GER",
    "Total Time" : "1:21.32",
    "Diff." : "+0.39",
    "FIS Points" : "4.53",
    "WC Points" : "0.00"
  }, {
    "Rank" : "5",
    "Bib" : "",
    "FIS Code" : "55198",
    "Name" : "DORFMEISTER Michaela",
    "Year" : "1973",
    "Nation" : "AUT",
    "Total Time" : "1:21.82",
    "Diff." : "+0.89",
    "FIS Points" : "10.34",
    "WC Points" : "0.00"
  }, {
    "Rank" : "6",
    "Bib" : "",
    "FIS Code" : "205378",
    "Name" : "ERTL Martina",
    "Year" : "1973",
    "Nation" : "GER",
    "Total Time" : "1:21.88",
    "Diff." : "+0.95",
    "FIS Points" : "11.03",
    "WC Points" : "0.00"
  }, {
    "Rank" : "7",
    "Bib" : "",
    "FIS Code" : "515142",
    "Name" : "ZURBRIGGEN Heidi",
    "Year" : "1967",
    "Nation" : "SUI",
    "Total Time" : "1:22.02",
    "Diff." : "+1.09",
    "FIS Points" : "12.66",
    "WC Points" : "0.00"
  }, {
    "Rank" : "8",
    "Bib" : "",
    "FIS Code" : "515138",
    "Name" : "ZELLER-BAEHLER Heidi",
    "Year" : "1967",
    "Nation" : "SUI",
    "Total Time" : "1:22.17",
    "Diff." : "+1.24",
    "FIS Points" : "14.40",
    "WC Points" : "0.00"
  }, {
    "Rank" : "9",
    "Bib" : "",
    "FIS Code" : "295267",
    "Name" : "COMPAGNONI Deborah",
    "Year" : "1970",
    "Nation" : "ITA",
    "Total Time" : "1:22.44",
    "Diff." : "+1.51",
    "FIS Points" : "17.54",
    "WC Points" : "0.00"
  }, {
    "Rank" : "10",
    "Bib" : "",
    "FIS Code" : "565097",
    "Name" : "PRETNAR Spela",
    "Year" : "1973",
    "Nation" : "SLO",
    "Total Time" : "1:22.81",
    "Diff." : "+1.88",
    "FIS Points" : "21.84",
    "WC Points" : "0.00"
  }, {
    "Rank" : "11",
    "Bib" : "",
    "FIS Code" : "505083",
    "Name" : "WIBERG Pernilla",
    "Year" : "1970",
    "Nation" : "SWE",
    "Total Time" : "1:22.87",
    "Diff." : "+1.94",
    "FIS Points" : "22.53",
    "WC Points" : "0.00"
  }, {
    "Rank" : "12",
    "Bib" : "",
    "FIS Code" : "205193",
    "Name" : "VOGT Miriam",
    "Year" : "1967",
    "Nation" : "GER",
    "Total Time" : "1:22.90",
    "Diff." : "+1.97",
    "FIS Points" : "22.88",
    "WC Points" : "0.00"
  }, {
    "Rank" : "13",
    "Bib" : "",
    "FIS Code" : "195195",
    "Name" : "CAVAGNOUD Regine",
    "Year" : "1970",
    "Nation" : "FRA",
    "Total Time" : "1:22.92",
    "Diff." : "+1.99",
    "FIS Points" : "23.11",
    "WC Points" : "0.00"
  }, {
    "Rank" : "14",
    "Bib" : "",
    "FIS Code" : "205445",
    "Name" : "GUTENSOHN Katharina",
    "Year" : "1966",
    "Nation" : "GER",
    "Total Time" : "1:22.94",
    "Diff." : "+2.01",
    "FIS Points" : "23.35",
    "WC Points" : "0.00"
  }, {
    "Rank" : "15",
    "Bib" : "",
    "FIS Code" : "485062",
    "Name" : "ZELENSKAJA Warwara",
    "Year" : "1972",
    "Nation" : "RUS",
    "Total Time" : "1:23.34",
    "Diff." : "+2.41",
    "FIS Points" : "27.99",
    "WC Points" : "0.00"
  }, {
    "Rank" : "16",
    "Bib" : "",
    "FIS Code" : "295191",
    "Name" : "MERLIN Barbara",
    "Year" : "1972",
    "Nation" : "ITA",
    "Total Time" : "1:23.61",
    "Diff." : "+2.68",
    "FIS Points" : "31.13",
    "WC Points" : "0.00"
  }, {
    "Rank" : "17",
    "Bib" : "",
    "FIS Code" : "425111",
    "Name" : "KJOERSTAD Marianne",
    "Year" : "1970",
    "Nation" : "NOR",
    "Total Time" : "1:23.62",
    "Diff." : "+2.69",
    "FIS Points" : "31.24",
    "WC Points" : "0.00"
  }, {
    "Rank" : "18",
    "Bib" : "",
    "FIS Code" : "535137",
    "Name" : "LINDH Hilary",
    "Year" : "1969",
    "Nation" : "USA",
    "Total Time" : "1:23.66",
    "Diff." : "+2.73",
    "FIS Points" : "31.71",
    "WC Points" : "0.00"
  }, {
    "Rank" : "19",
    "Bib" : "",
    "FIS Code" : "205117",
    "Name" : "GERG Hilde",
    "Year" : "1975",
    "Nation" : "GER",
    "Total Time" : "1:24.75",
    "Diff." : "+3.82",
    "FIS Points" : "44.37",
    "WC Points" : "0.00"
  }, {
    "Rank" : "Disqualified 1st run"
  }, {
    "Rank" : ""
  }, {
    "Rank" : "",
    "Bib" : "",
    "FIS Code" : "105101",
    "Name" : "PACE LINDSAY Kate",
    "Year" : "1969",
    "Nation" : "CAN",
    "Total Time" : "",
    "Diff." : "",
    "FIS Points" : "",
    "WC Points" : "0.00"
  }, {
    "Rank" : "Did not finish 1st run"
  }, {
    "Rank" : ""
  }, {
    "Rank" : "",
    "Bib" : "",
    "FIS Code" : "535327",
    "Name" : "NOBIS Shannon",
    "Year" : "1972",
    "Nation" : "USA",
    "Total Time" : "",
    "Diff." : "",
    "FIS Points" : "",
    "WC Points" : "0.00"
  }, {
    "Rank" : "",
    "Bib" : "",
    "FIS Code" : "55212",
    "Name" : "MEISSNITZER Alexandra",
    "Year" : "1973",
    "Nation" : "AUT",
    "Total Time" : "",
    "Diff." : "",
    "FIS Points" : "",
    "WC Points" : "0.00"
  }, {
    "Rank" : "",
    "Bib" : "",
    "FIS Code" : "535503",
    "Name" : "STREET Picabo",
    "Year" : "1971",
    "Nation" : "USA",
    "Total Time" : "",
    "Diff." : "",
    "FIS Points" : "",
    "WC Points" : "0.00"
  }, {
    "Rank" : "",
    "Bib" : "",
    "FIS Code" : "515106",
    "Name" : "SCHNEIDER Vreni",
    "Year" : "1964",
    "Nation" : "SUI",
    "Total Time" : "",
    "Diff." : "",
    "FIS Points" : "",
    "WC Points" : "0.00"
  }, {
    "Rank" : "",
    "Bib" : "",
    "FIS Code" : "55020",
    "Name" : "EDER Sylvia",
    "Year" : "1965",
    "Nation" : "AUT",
    "Total Time" : "",
    "Diff." : "",
    "FIS Points" : "",
    "WC Points" : "0.00"
  }, {
    "Rank" : "",
    "Bib" : "",
    "FIS Code" : "515075",
    "Name" : "BRIGGER-SUMMERMATTER Madlen",
    "Year" : "1974",
    "Nation" : "SUI",
    "Total Time" : "",
    "Diff." : "",
    "FIS Points" : "",
    "WC Points" : "0.00"
  }, {
    "Rank" : ""
  } ]
}