{
  "raceInfo" : {
    "Jury" : {
      "TD FIS" : {
        "name" : "",
        "country" : ""
      },
      "Referee" : {
        "name" : "",
        "country" : ""
      },
      "Chief of Race" : {
        "name" : "",
        "country" : ""
      }
    },
    "Technical Data" : {
      "Start Altitude" : "m.",
      "Finish Altitude" : "m.",
      "Vertical Drop" : "0 m.",
      "Homologation Number" : ""
    }
  },
  "results" : [ {
    "Rank" : "1",
    "Bib" : "",
    "FIS Code" : "510318",
    "Name" : "VON GRUENIGEN Michael",
    "Year" : "1969",
    "Nation" : "SUI",
    "Run 1" : "",
    "Run 2" : "",
    "Total Time" : "2:25.09",
    "Diff." : "",
    "FIS Points" : "0.00",
    "WC Points" : "0.00"
  }, {
    "Rank" : "2",
    "Bib" : "",
    "FIS Code" : "420382",
    "Name" : "AAMODT Kjetil Andre",
    "Year" : "1971",
    "Nation" : "NOR",
    "Run 1" : "",
    "Run 2" : "",
    "Total Time" : "2:25.90",
    "Diff." : "+0.81",
    "FIS Points" : "4.35",
    "WC Points" : "0.00"
  }, {
    "Rank" : "3",
    "Bib" : "",
    "FIS Code" : "50127",
    "Name" : "MADER Guenther",
    "Year" : "1964",
    "Nation" : "AUT",
    "Run 1" : "",
    "Run 2" : "",
    "Total Time" : "2:26.84",
    "Diff." : "+1.75",
    "FIS Points" : "9.41",
    "WC Points" : "0.00"
  }, {
    "Rank" : "4",
    "Bib" : "",
    "FIS Code" : "510125",
    "Name" : "KAELIN Urs",
    "Year" : "1966",
    "Nation" : "SUI",
    "Run 1" : "",
    "Run 2" : "",
    "Total Time" : "2:27.03",
    "Diff." : "+1.94",
    "FIS Points" : "10.43",
    "WC Points" : "0.00"
  }, {
    "Rank" : "4",
    "Bib" : "",
    "FIS Code" : "420470",
    "Name" : "KJUS Lasse",
    "Year" : "1971",
    "Nation" : "NOR",
    "Run 1" : "",
    "Run 2" : "",
    "Total Time" : "2:27.03",
    "Diff." : "+1.94",
    "FIS Points" : "10.43",
    "WC Points" : "0.00"
  }, {
    "Rank" : "6",
    "Bib" : "",
    "FIS Code" : "510145",
    "Name" : "LOCHER Steve",
    "Year" : "1967",
    "Nation" : "SUI",
    "Run 1" : "",
    "Run 2" : "",
    "Total Time" : "2:27.46",
    "Diff." : "+2.37",
    "FIS Points" : "12.74",
    "WC Points" : "0.00"
  }, {
    "Rank" : "7",
    "Bib" : "",
    "FIS Code" : "560033",
    "Name" : "KOSIR Jure",
    "Year" : "1972",
    "Nation" : "SLO",
    "Run 1" : "",
    "Run 2" : "",
    "Total Time" : "2:27.82",
    "Diff." : "+2.73",
    "FIS Points" : "14.68",
    "WC Points" : "0.00"
  }, {
    "Rank" : "8",
    "Bib" : "",
    "FIS Code" : "200008",
    "Name" : "BARNERSSOI Tobias",
    "Year" : "1969",
    "Nation" : "GER",
    "Run 1" : "",
    "Run 2" : "",
    "Total Time" : "2:27.89",
    "Diff." : "+2.80",
    "FIS Points" : "15.05",
    "WC Points" : "0.00"
  }, {
    "Rank" : "9",
    "Bib" : "",
    "FIS Code" : "420556",
    "Name" : "STRAND NILSEN Harald Chr.",
    "Year" : "1971",
    "Nation" : "NOR",
    "Run 1" : "",
    "Run 2" : "",
    "Total Time" : "2:28.21",
    "Diff." : "+3.12",
    "FIS Points" : "16.77",
    "WC Points" : "0.00"
  }, {
    "Rank" : "10",
    "Bib" : "",
    "FIS Code" : "190270",
    "Name" : "PICCARD Ian",
    "Year" : "1968",
    "Nation" : "FRA",
    "Run 1" : "",
    "Run 2" : "",
    "Total Time" : "2:28.24",
    "Diff." : "+3.15",
    "FIS Points" : "16.93",
    "WC Points" : "0.00"
  }, {
    "Rank" : "11",
    "Bib" : "",
    "FIS Code" : "350031",
    "Name" : "VOGT Achim",
    "Year" : "1970",
    "Nation" : "LIE",
    "Run 1" : "",
    "Run 2" : "",
    "Total Time" : "2:28.38",
    "Diff." : "+3.29",
    "FIS Points" : "17.69",
    "WC Points" : "0.00"
  }, {
    "Rank" : "12",
    "Bib" : "",
    "FIS Code" : "291019",
    "Name" : "ZUCCHELLI Massimo",
    "Year" : "1972",
    "Nation" : "ITA",
    "Run 1" : "",
    "Run 2" : "",
    "Total Time" : "2:28.47",
    "Diff." : "+3.38",
    "FIS Points" : "18.17",
    "WC Points" : "0.00"
  }, {
    "Rank" : "13",
    "Bib" : "",
    "FIS Code" : "50126",
    "Name" : "MAYER Christian",
    "Year" : "1972",
    "Nation" : "AUT",
    "Run 1" : "",
    "Run 2" : "",
    "Total Time" : "2:28.50",
    "Diff." : "+3.41",
    "FIS Points" : "18.33",
    "WC Points" : "0.00"
  }, {
    "Rank" : "13",
    "Bib" : "",
    "FIS Code" : "360002",
    "Name" : "GIRARDELLI Marc",
    "Year" : "1963",
    "Nation" : "LUX",
    "Run 1" : "",
    "Run 2" : "",
    "Total Time" : "2:28.50",
    "Diff." : "+3.41",
    "FIS Points" : "18.33",
    "WC Points" : "0.00"
  }, {
    "Rank" : "15",
    "Bib" : "",
    "FIS Code" : "510106",
    "Name" : "HANGL Marco",
    "Year" : "1967",
    "Nation" : "SUI",
    "Run 1" : "",
    "Run 2" : "",
    "Total Time" : "2:28.81",
    "Diff." : "+3.72",
    "FIS Points" : "20.00",
    "WC Points" : "0.00"
  }, {
    "Rank" : "16",
    "Bib" : "",
    "FIS Code" : "50117",
    "Name" : "KROELL Richard",
    "Year" : "1968",
    "Nation" : "AUT",
    "Run 1" : "",
    "Run 2" : "",
    "Total Time" : "2:28.88",
    "Diff." : "+3.79",
    "FIS Points" : "20.37",
    "WC Points" : "0.00"
  }, {
    "Rank" : "17",
    "Bib" : "",
    "FIS Code" : "500106",
    "Name" : "WALLNER Johan",
    "Year" : "1965",
    "Nation" : "SWE",
    "Run 1" : "",
    "Run 2" : "",
    "Total Time" : "2:29.21",
    "Diff." : "+4.12",
    "FIS Points" : "22.15",
    "WC Points" : "0.00"
  }, {
    "Rank" : "18",
    "Bib" : "",
    "FIS Code" : "190268",
    "Name" : "PICCARD Franck",
    "Year" : "1964",
    "Nation" : "FRA",
    "Run 1" : "",
    "Run 2" : "",
    "Total Time" : "2:29.26",
    "Diff." : "+4.17",
    "FIS Points" : "22.42",
    "WC Points" : "0.00"
  }, {
    "Rank" : "19",
    "Bib" : "",
    "FIS Code" : "290404",
    "Name" : "PESANDO Luca",
    "Year" : "1966",
    "Nation" : "ITA",
    "Run 1" : "",
    "Run 2" : "",
    "Total Time" : "2:29.51",
    "Diff." : "+4.42",
    "FIS Points" : "23.76",
    "WC Points" : "0.00"
  }, {
    "Rank" : "20",
    "Bib" : "",
    "FIS Code" : "510001",
    "Name" : "ACCOLA Paul",
    "Year" : "1967",
    "Nation" : "SUI",
    "Run 1" : "",
    "Run 2" : "",
    "Total Time" : "2:29.60",
    "Diff." : "+4.51",
    "FIS Points" : "24.25",
    "WC Points" : "0.00"
  }, {
    "Rank" : "21",
    "Bib" : "",
    "FIS Code" : "190314",
    "Name" : "SAIONI Christophe",
    "Year" : "1969",
    "Nation" : "FRA",
    "Run 1" : "",
    "Run 2" : "",
    "Total Time" : "2:29.61",
    "Diff." : "+4.52",
    "FIS Points" : "24.30",
    "WC Points" : "0.00"
  }, {
    "Rank" : "22",
    "Bib" : "",
    "FIS Code" : "560154",
    "Name" : "KUNC Mitja",
    "Year" : "1971",
    "Nation" : "SLO",
    "Run 1" : "",
    "Run 2" : "",
    "Total Time" : "2:29.62",
    "Diff." : "+4.53",
    "FIS Points" : "24.35",
    "WC Points" : "0.00"
  }, {
    "Rank" : "23",
    "Bib" : "",
    "FIS Code" : "50360",
    "Name" : "KNAUSS Hans",
    "Year" : "1971",
    "Nation" : "AUT",
    "Run 1" : "",
    "Run 2" : "",
    "Total Time" : "2:29.66",
    "Diff." : "+4.57",
    "FIS Points" : "24.57",
    "WC Points" : "0.00"
  }, {
    "Rank" : "24",
    "Bib" : "",
    "FIS Code" : "290803",
    "Name" : "BERGAMELLI Norman",
    "Year" : "1971",
    "Nation" : "ITA",
    "Run 1" : "",
    "Run 2" : "",
    "Total Time" : "2:29.83",
    "Diff." : "+4.74",
    "FIS Points" : "25.48",
    "WC Points" : "0.00"
  }, {
    "Rank" : "25",
    "Bib" : "",
    "FIS Code" : "560151",
    "Name" : "KOBLAR Jernej",
    "Year" : "1971",
    "Nation" : "SLO",
    "Run 1" : "",
    "Run 2" : "",
    "Total Time" : "2:30.35",
    "Diff." : "+5.26",
    "FIS Points" : "28.28",
    "WC Points" : "0.00"
  }, {
    "Rank" : "26",
    "Bib" : "",
    "FIS Code" : "190112",
    "Name" : "DIMIER Yves",
    "Year" : "1969",
    "Nation" : "FRA",
    "Run 1" : "",
    "Run 2" : "",
    "Total Time" : "2:30.47",
    "Diff." : "+5.38",
    "FIS Points" : "28.92",
    "WC Points" : "0.00"
  }, {
    "Rank" : "27",
    "Bib" : "",
    "FIS Code" : "510326",
    "Name" : "EGGENBERGER Yvan",
    "Year" : "1969",
    "Nation" : "SUI",
    "Run 1" : "",
    "Run 2" : "",
    "Total Time" : "2:30.90",
    "Diff." : "+5.81",
    "FIS Points" : "31.23",
    "WC Points" : "0.00"
  }, {
    "Rank" : "28",
    "Bib" : "",
    "FIS Code" : "50069",
    "Name" : "GSTREIN Bernhard",
    "Year" : "1965",
    "Nation" : "AUT",
    "Run 1" : "",
    "Run 2" : "",
    "Total Time" : "2:30.94",
    "Diff." : "+5.85",
    "FIS Points" : "31.45",
    "WC Points" : "0.00"
  }, {
    "Rank" : "Disqualified 1st run"
  }, {
    "Rank" : ""
  }, {
    "Rank" : "",
    "Bib" : "",
    "FIS Code" : "510478",
    "Name" : "KERNEN Bruno Ii",
    "Year" : "1972",
    "Nation" : "SUI",
    "Run 1" : "",
    "Run 2" : "",
    "Total Time" : "",
    "Diff." : "",
    "FIS Points" : "",
    "WC Points" : "0.00"
  }, {
    "Rank" : "Did not start 2nd run"
  }, {
    "Rank" : ""
  }, {
    "Rank" : "",
    "Bib" : "",
    "FIS Code" : "290539",
    "Name" : "TOMBA Alberto",
    "Year" : "1966",
    "Nation" : "ITA",
    "Run 1" : "",
    "Run 2" : "",
    "Total Time" : "",
    "Diff." : "",
    "FIS Points" : "",
    "WC Points" : "0.00"
  }, {
    "Rank" : "Did not qualify for 2nd run"
  }, {
    "Rank" : ""
  }, {
    "Rank" : "",
    "Bib" : "",
    "FIS Code" : "290299",
    "Name" : "KOENIGSRAINER Gerhard",
    "Year" : "1968",
    "Nation" : "ITA",
    "Run 1" : "",
    "Run 2" : "",
    "Total Time" : "",
    "Diff." : "",
    "FIS Points" : "",
    "WC Points" : "0.00"
  }, {
    "Rank" : "",
    "Bib" : "",
    "FIS Code" : "290705",
    "Name" : "HOLZER Patrick",
    "Year" : "1970",
    "Nation" : "ITA",
    "Run 1" : "",
    "Run 2" : "",
    "Total Time" : "",
    "Diff." : "",
    "FIS Points" : "",
    "WC Points" : "0.00"
  }, {
    "Rank" : "",
    "Bib" : "",
    "FIS Code" : "180121",
    "Name" : "MARILA Mika",
    "Year" : "1973",
    "Nation" : "FIN",
    "Run 1" : "",
    "Run 2" : "",
    "Total Time" : "",
    "Diff." : "",
    "FIS Points" : "",
    "WC Points" : "0.00"
  }, {
    "Rank" : "",
    "Bib" : "",
    "FIS Code" : "100115",
    "Name" : "GRANDI Thomas",
    "Year" : "1972",
    "Nation" : "CAN",
    "Run 1" : "",
    "Run 2" : "",
    "Total Time" : "",
    "Diff." : "",
    "FIS Points" : "",
    "WC Points" : "0.00"
  }, {
    "Rank" : "",
    "Bib" : "",
    "FIS Code" : "190136",
    "Name" : "FEUTRIER Alain",
    "Year" : "1968",
    "Nation" : "FRA",
    "Run 1" : "",
    "Run 2" : "",
    "Total Time" : "",
    "Diff." : "",
    "FIS Points" : "",
    "WC Points" : "0.00"
  }, {
    "Rank" : "",
    "Bib" : "",
    "FIS Code" : "560115",
    "Name" : "MIKLAVC Andrej",
    "Year" : "1970",
    "Nation" : "SLO",
    "Run 1" : "",
    "Run 2" : "",
    "Total Time" : "",
    "Diff." : "",
    "FIS Points" : "",
    "WC Points" : "0.00"
  }, {
    "Rank" : "",
    "Bib" : "",
    "FIS Code" : "490088",
    "Name" : "CRISTOBAL GALLARDO Luis A.",
    "Year" : "1970",
    "Nation" : "ESP",
    "Run 1" : "",
    "Run 2" : "",
    "Total Time" : "",
    "Diff." : "",
    "FIS Points" : "",
    "WC Points" : "0.00"
  }, {
    "Rank" : "",
    "Bib" : "",
    "FIS Code" : "380185",
    "Name" : "PAVLEK Vedran",
    "Year" : "1973",
    "Nation" : "CRO",
    "Run 1" : "",
    "Run 2" : "",
    "Total Time" : "",
    "Diff." : "",
    "FIS Points" : "",
    "WC Points" : "0.00"
  }, {
    "Rank" : "",
    "Bib" : "",
    "FIS Code" : "100465",
    "Name" : "PODIVINSKY Ed",
    "Year" : "1970",
    "Nation" : "CAN",
    "Run 1" : "",
    "Run 2" : "",
    "Total Time" : "",
    "Diff." : "",
    "FIS Points" : "",
    "WC Points" : "0.00"
  }, {
    "Rank" : "",
    "Bib" : "",
    "FIS Code" : "530562",
    "Name" : "PUCKETT Christopher",
    "Year" : "1970",
    "Nation" : "USA",
    "Run 1" : "",
    "Run 2" : "",
    "Total Time" : "",
    "Diff." : "",
    "FIS Points" : "",
    "WC Points" : "0.00"
  }, {
    "Rank" : "",
    "Bib" : "",
    "FIS Code" : "510291",
    "Name" : "BORTIS Michel",
    "Year" : "1970",
    "Nation" : "SUI",
    "Run 1" : "",
    "Run 2" : "",
    "Total Time" : "",
    "Diff." : "",
    "FIS Points" : "",
    "WC Points" : "0.00"
  }, {
    "Rank" : "",
    "Bib" : "",
    "FIS Code" : "510094",
    "Name" : "ROTEN Joerg",
    "Year" : "1974",
    "Nation" : "SUI",
    "Run 1" : "",
    "Run 2" : "",
    "Total Time" : "",
    "Diff." : "",
    "FIS Points" : "",
    "WC Points" : "0.00"
  }, {
    "Rank" : "",
    "Bib" : "",
    "FIS Code" : "50171",
    "Name" : "SALZGEBER Rainer",
    "Year" : "1967",
    "Nation" : "AUT",
    "Run 1" : "",
    "Run 2" : "",
    "Total Time" : "",
    "Diff." : "",
    "FIS Points" : "",
    "WC Points" : "0.00"
  }, {
    "Rank" : "",
    "Bib" : "",
    "FIS Code" : "200249",
    "Name" : "STANKALLA Stefan",
    "Year" : "1975",
    "Nation" : "GER",
    "Run 1" : "",
    "Run 2" : "",
    "Total Time" : "",
    "Diff." : "",
    "FIS Points" : "",
    "WC Points" : "0.00"
  }, {
    "Rank" : "",
    "Bib" : "",
    "FIS Code" : "420136",
    "Name" : "MELBY Sverre",
    "Year" : "1968",
    "Nation" : "NOR",
    "Run 1" : "",
    "Run 2" : "",
    "Total Time" : "",
    "Diff." : "",
    "FIS Points" : "",
    "WC Points" : "0.00"
  }, {
    "Rank" : "",
    "Bib" : "",
    "FIS Code" : "190707",
    "Name" : "MILLET Vincent",
    "Year" : "1973",
    "Nation" : "FRA",
    "Run 1" : "",
    "Run 2" : "",
    "Total Time" : "",
    "Diff." : "",
    "FIS Points" : "",
    "WC Points" : "0.00"
  }, {
    "Rank" : "",
    "Bib" : "",
    "FIS Code" : "500139",
    "Name" : "NYBERG Fredrik",
    "Year" : "1969",
    "Nation" : "SWE",
    "Run 1" : "",
    "Run 2" : "",
    "Total Time" : "",
    "Diff." : "",
    "FIS Points" : "",
    "WC Points" : "0.00"
  }, {
    "Rank" : "",
    "Bib" : "",
    "FIS Code" : "530548",
    "Name" : "NOBIS Jeremy",
    "Year" : "1970",
    "Nation" : "USA",
    "Run 1" : "",
    "Run 2" : "",
    "Total Time" : "",
    "Diff." : "",
    "FIS Points" : "",
    "WC Points" : "0.00"
  }, {
    "Rank" : "",
    "Bib" : "",
    "FIS Code" : "290042",
    "Name" : "BELFROND Matteo",
    "Year" : "1967",
    "Nation" : "ITA",
    "Run 1" : "",
    "Run 2" : "",
    "Total Time" : "",
    "Diff." : "",
    "FIS Points" : "",
    "WC Points" : "0.00"
  }, {
    "Rank" : "",
    "Bib" : "",
    "FIS Code" : "430233",
    "Name" : "EXARTIER Stephane",
    "Year" : "1969",
    "Nation" : "POL",
    "Run 1" : "",
    "Run 2" : "",
    "Total Time" : "",
    "Diff." : "",
    "FIS Points" : "",
    "WC Points" : "0.00"
  }, {
    "Rank" : "",
    "Bib" : "",
    "FIS Code" : "420059",
    "Name" : "FURUSETH Ole Christian",
    "Year" : "1967",
    "Nation" : "NOR",
    "Run 1" : "",
    "Run 2" : "",
    "Total Time" : "",
    "Diff." : "",
    "FIS Points" : "",
    "WC Points" : "0.00"
  }, {
    "Rank" : "",
    "Bib" : "",
    "FIS Code" : "50309",
    "Name" : "REITER Mario",
    "Year" : "1970",
    "Nation" : "AUT",
    "Run 1" : "",
    "Run 2" : "",
    "Total Time" : "",
    "Diff." : "",
    "FIS Points" : "",
    "WC Points" : "0.00"
  }, {
    "Rank" : "",
    "Bib" : "",
    "FIS Code" : "420182",
    "Name" : "SKAARDAL Atle",
    "Year" : "1966",
    "Nation" : "NOR",
    "Run 1" : "",
    "Run 2" : "",
    "Total Time" : "",
    "Diff." : "",
    "FIS Points" : "",
    "WC Points" : "0.00"
  }, {
    "Rank" : "",
    "Bib" : "",
    "FIS Code" : "420328",
    "Name" : "STIANSEN Tom",
    "Year" : "1970",
    "Nation" : "NOR",
    "Run 1" : "",
    "Run 2" : "",
    "Total Time" : "",
    "Diff." : "",
    "FIS Points" : "",
    "WC Points" : "0.00"
  }, {
    "Rank" : "",
    "Bib" : "",
    "FIS Code" : "50149",
    "Name" : "STROBL Josef",
    "Year" : "1974",
    "Nation" : "AUT",
    "Run 1" : "",
    "Run 2" : "",
    "Total Time" : "",
    "Diff." : "",
    "FIS Points" : "",
    "WC Points" : "0.00"
  }, {
    "Rank" : "",
    "Bib" : "",
    "FIS Code" : "510240",
    "Name" : "SULLIGER Marcel",
    "Year" : "1967",
    "Nation" : "SUI",
    "Run 1" : "",
    "Run 2" : "",
    "Total Time" : "",
    "Diff." : "",
    "FIS Points" : "",
    "WC Points" : "0.00"
  }, {
    "Rank" : "",
    "Bib" : "",
    "FIS Code" : "420670",
    "Name" : "TORPE Are",
    "Year" : "1973",
    "Nation" : "NOR",
    "Run 1" : "",
    "Run 2" : "",
    "Total Time" : "",
    "Diff." : "",
    "FIS Points" : "",
    "WC Points" : "0.00"
  }, {
    "Rank" : "",
    "Bib" : "",
    "FIS Code" : "200251",
    "Name" : "VOGL Alois",
    "Year" : "1972",
    "Nation" : "GER",
    "Run 1" : "",
    "Run 2" : "",
    "Total Time" : "",
    "Diff." : "",
    "FIS Points" : "",
    "WC Points" : "0.00"
  }, {
    "Rank" : "",
    "Bib" : "",
    "FIS Code" : "290062",
    "Name" : "BORMOLINI Ivan",
    "Year" : "1972",
    "Nation" : "ITA",
    "Run 1" : "",
    "Run 2" : "",
    "Total Time" : "",
    "Diff." : "",
    "FIS Points" : "",
    "WC Points" : "0.00"
  }, {
    "Rank" : "Did not finish 2nd run"
  }, {
    "Rank" : ""
  }, {
    "Rank" : "",
    "Bib" : "",
    "FIS Code" : "50230",
    "Name" : "VOGLREITER Siegfried",
    "Year" : "1969",
    "Nation" : "AUT",
    "Run 1" : "",
    "Run 2" : "",
    "Total Time" : "",
    "Diff." : "",
    "FIS Points" : "",
    "WC Points" : "0.00"
  }, {
    "Rank" : "Did not finish 1st run"
  }, {
    "Rank" : ""
  }, {
    "Rank" : "",
    "Bib" : "",
    "FIS Code" : "500150",
    "Name" : "JAERBYN Patrik",
    "Year" : "1969",
    "Nation" : "SWE",
    "Run 1" : "",
    "Run 2" : "",
    "Total Time" : "",
    "Diff." : "",
    "FIS Points" : "",
    "WC Points" : "0.00"
  }, {
    "Rank" : "",
    "Bib" : "",
    "FIS Code" : "40204",
    "Name" : "HUGUET Anthony",
    "Year" : "1973",
    "Nation" : "AUS",
    "Run 1" : "",
    "Run 2" : "",
    "Total Time" : "",
    "Diff." : "",
    "FIS Points" : "",
    "WC Points" : "0.00"
  }, {
    "Rank" : "",
    "Bib" : "",
    "FIS Code" : "290426",
    "Name" : "POLIG Josef",
    "Year" : "1968",
    "Nation" : "ITA",
    "Run 1" : "",
    "Run 2" : "",
    "Total Time" : "",
    "Diff." : "",
    "FIS Points" : "",
    "WC Points" : "0.00"
  }, {
    "Rank" : "",
    "Bib" : "",
    "FIS Code" : "200056",
    "Name" : "ERTL Andreas",
    "Year" : "1975",
    "Nation" : "GER",
    "Run 1" : "",
    "Run 2" : "",
    "Total Time" : "",
    "Diff." : "",
    "FIS Points" : "",
    "WC Points" : "0.00"
  }, {
    "Rank" : "",
    "Bib" : "",
    "FIS Code" : "350032",
    "Name" : "BUECHEL Marco",
    "Year" : "1971",
    "Nation" : "LIE",
    "Run 1" : "",
    "Run 2" : "",
    "Total Time" : "",
    "Diff." : "",
    "FIS Points" : "",
    "WC Points" : "0.00"
  }, {
    "Rank" : ""
  } ],
  "eventInfo" : {
    "Date" : "18.12.1994",
    "Place" : "Val d'Isere",
    "Nation" : "FRA",
    "Codex" : "0104",
    "Discipline" : "Giant Slalom",
    "Gender" : "M",
    "Category" : "WC",
    "Comments" : "",
    "Down load" : ""
  }
}