{
  "result" : [ {
    "Rank" : "1",
    "Bib" : "11",
    "FIS Code" : "510993",
    "Name" : "ALBRECHT Daniel",
    "Year" : "1983",
    "Nation" : "SUI",
    "Run 1" : "1:14.11",
    "Run 2" : "1:10.19",
    "Total Time" : "2:24.30",
    "Diff." : "",
    "FIS Points" : "0.00",
    "WC Points" : "100.00"
  }, {
    "Rank" : "2",
    "Bib" : "20",
    "FIS Code" : "50707",
    "Name" : "MATT Mario",
    "Year" : "1979",
    "Nation" : "AUT",
    "Run 1" : "1:14.07",
    "Run 2" : "1:10.28",
    "Total Time" : "2:24.35",
    "Diff." : "+0.05",
    "FIS Points" : "0.30",
    "WC Points" : "80.00"
  }, {
    "Rank" : "3",
    "Bib" : "3",
    "FIS Code" : "510030",
    "Name" : "CUCHE Didier",
    "Year" : "1974",
    "Nation" : "SUI",
    "Run 1" : "1:13.06",
    "Run 2" : "1:11.35",
    "Total Time" : "2:24.41",
    "Diff." : "+0.11",
    "FIS Points" : "0.67",
    "WC Points" : "60.00"
  }, {
    "Rank" : "4",
    "Bib" : "6",
    "FIS Code" : "534562",
    "Name" : "LIGETY Ted",
    "Year" : "1984",
    "Nation" : "USA",
    "Run 1" : "1:13.66",
    "Run 2" : "1:10.79",
    "Total Time" : "2:24.45",
    "Diff." : "+0.15",
    "FIS Points" : "0.91",
    "WC Points" : "50.00"
  }, {
    "Rank" : "4",
    "Bib" : "2",
    "FIS Code" : "292000",
    "Name" : "BLARDONE Massimiliano",
    "Year" : "1979",
    "Nation" : "ITA",
    "Run 1" : "1:13.18",
    "Run 2" : "1:11.27",
    "Total Time" : "2:24.45",
    "Diff." : "+0.15",
    "FIS Points" : "0.91",
    "WC Points" : "50.00"
  }, {
    "Rank" : "6",
    "Bib" : "10",
    "FIS Code" : "102873",
    "Name" : "KUCERA John",
    "Year" : "1984",
    "Nation" : "CAN",
    "Run 1" : "1:13.74",
    "Run 2" : "1:10.77",
    "Total Time" : "2:24.51",
    "Diff." : "+0.21",
    "FIS Points" : "1.28",
    "WC Points" : "40.00"
  }, {
    "Rank" : "7",
    "Bib" : "22",
    "FIS Code" : "50742",
    "Name" : "REICHELT Hannes",
    "Year" : "1980",
    "Nation" : "AUT",
    "Run 1" : "1:13.92",
    "Run 2" : "1:10.87",
    "Total Time" : "2:24.79",
    "Diff." : "+0.49",
    "FIS Points" : "2.99",
    "WC Points" : "36.00"
  }, {
    "Rank" : "8",
    "Bib" : "7",
    "FIS Code" : "50625",
    "Name" : "RAICH Benjamin",
    "Year" : "1978",
    "Nation" : "AUT",
    "Run 1" : "1:13.59",
    "Run 2" : "1:11.27",
    "Total Time" : "2:24.86",
    "Diff." : "+0.56",
    "FIS Points" : "3.42",
    "WC Points" : "32.00"
  }, {
    "Rank" : "9",
    "Bib" : "4",
    "FIS Code" : "102814",
    "Name" : "BOURQUE Francois",
    "Year" : "1984",
    "Nation" : "CAN",
    "Run 1" : "1:14.11",
    "Run 2" : "1:10.77",
    "Total Time" : "2:24.88",
    "Diff." : "+0.58",
    "FIS Points" : "3.54",
    "WC Points" : "29.00"
  }, {
    "Rank" : "10",
    "Bib" : "17",
    "FIS Code" : "50451",
    "Name" : "GRUBER Christoph",
    "Year" : "1976",
    "Nation" : "AUT",
    "Run 1" : "1:13.86",
    "Run 2" : "1:11.04",
    "Total Time" : "2:24.90",
    "Diff." : "+0.60",
    "FIS Points" : "3.66",
    "WC Points" : "26.00"
  }, {
    "Rank" : "10",
    "Bib" : "13",
    "FIS Code" : "191750",
    "Name" : "FANARA Thomas",
    "Year" : "1981",
    "Nation" : "FRA",
    "Run 1" : "1:14.67",
    "Run 2" : "1:10.23",
    "Total Time" : "2:24.90",
    "Diff." : "+0.60",
    "FIS Points" : "3.66",
    "WC Points" : "26.00"
  }, {
    "Rank" : "12",
    "Bib" : "12",
    "FIS Code" : "292491",
    "Name" : "MOELGG Manfred",
    "Year" : "1982",
    "Nation" : "ITA",
    "Run 1" : "1:13.59",
    "Run 2" : "1:11.44",
    "Total Time" : "2:25.03",
    "Diff." : "+0.73",
    "FIS Points" : "4.45",
    "WC Points" : "22.00"
  }, {
    "Rank" : "13",
    "Bib" : "18",
    "FIS Code" : "51005",
    "Name" : "SCHEIBER Mario",
    "Year" : "1983",
    "Nation" : "AUT",
    "Run 1" : "1:14.59",
    "Run 2" : "1:10.48",
    "Total Time" : "2:25.07",
    "Diff." : "+0.77",
    "FIS Points" : "4.70",
    "WC Points" : "20.00"
  }, {
    "Rank" : "14",
    "Bib" : "16",
    "FIS Code" : "50423",
    "Name" : "MAIER Hermann",
    "Year" : "1972",
    "Nation" : "AUT",
    "Run 1" : "1:14.52",
    "Run 2" : "1:10.87",
    "Total Time" : "2:25.39",
    "Diff." : "+1.09",
    "FIS Points" : "6.65",
    "WC Points" : "18.00"
  }, {
    "Rank" : "15",
    "Bib" : "24",
    "FIS Code" : "50600",
    "Name" : "GOERGL Stephan",
    "Year" : "1978",
    "Nation" : "AUT",
    "Run 1" : "1:14.47",
    "Run 2" : "1:10.93",
    "Total Time" : "2:25.40",
    "Diff." : "+1.10",
    "FIS Points" : "6.71",
    "WC Points" : "16.00"
  }, {
    "Rank" : "15",
    "Bib" : "19",
    "FIS Code" : "292455",
    "Name" : "FILL Peter",
    "Year" : "1982",
    "Nation" : "ITA",
    "Run 1" : "1:14.12",
    "Run 2" : "1:11.28",
    "Total Time" : "2:25.40",
    "Diff." : "+1.10",
    "FIS Points" : "6.71",
    "WC Points" : "16.00"
  }, {
    "Rank" : "17",
    "Bib" : "40",
    "FIS Code" : "180534",
    "Name" : "SANDELL Marcus",
    "Year" : "1987",
    "Nation" : "FIN",
    "Run 1" : "1:14.83",
    "Run 2" : "1:10.59",
    "Total Time" : "2:25.42",
    "Diff." : "+1.12",
    "FIS Points" : "6.83",
    "WC Points" : "14.00"
  }, {
    "Rank" : "18",
    "Bib" : "43",
    "FIS Code" : "511313",
    "Name" : "JANKA Carlo",
    "Year" : "1986",
    "Nation" : "SUI",
    "Run 1" : "1:14.93",
    "Run 2" : "1:10.50",
    "Total Time" : "2:25.43",
    "Diff." : "+1.13",
    "FIS Points" : "6.89",
    "WC Points" : "13.00"
  }, {
    "Rank" : "19",
    "Bib" : "9",
    "FIS Code" : "190677",
    "Name" : "CHENAL Joel",
    "Year" : "1973",
    "Nation" : "FRA",
    "Run 1" : "1:14.24",
    "Run 2" : "1:11.24",
    "Total Time" : "2:25.48",
    "Diff." : "+1.18",
    "FIS Points" : "7.20",
    "WC Points" : "12.00"
  }, {
    "Rank" : "20",
    "Bib" : "15",
    "FIS Code" : "292120",
    "Name" : "SIMONCELLI Davide",
    "Year" : "1979",
    "Nation" : "ITA",
    "Run 1" : "1:14.53",
    "Run 2" : "1:10.98",
    "Total Time" : "2:25.51",
    "Diff." : "+1.21",
    "FIS Points" : "7.38",
    "WC Points" : "11.00"
  }, {
    "Rank" : "21",
    "Bib" : "25",
    "FIS Code" : "530703",
    "Name" : "SCHLOPY Erik",
    "Year" : "1972",
    "Nation" : "USA",
    "Run 1" : "1:14.46",
    "Run 2" : "1:11.08",
    "Total Time" : "2:25.54",
    "Diff." : "+1.24",
    "FIS Points" : "7.56",
    "WC Points" : "10.00"
  }, {
    "Rank" : "22",
    "Bib" : "27",
    "FIS Code" : "560406",
    "Name" : "GORZA Ales",
    "Year" : "1980",
    "Nation" : "SLO",
    "Run 1" : "1:14.31",
    "Run 2" : "1:11.34",
    "Total Time" : "2:25.65",
    "Diff." : "+1.35",
    "FIS Points" : "8.23",
    "WC Points" : "9.00"
  }, {
    "Rank" : "23",
    "Bib" : "30",
    "FIS Code" : "420148",
    "Name" : "KARLSEN Truls Ove",
    "Year" : "1975",
    "Nation" : "NOR",
    "Run 1" : "1:14.65",
    "Run 2" : "1:11.08",
    "Total Time" : "2:25.73",
    "Diff." : "+1.43",
    "FIS Points" : "8.72",
    "WC Points" : "8.00"
  }, {
    "Rank" : "24",
    "Bib" : "39",
    "FIS Code" : "191423",
    "Name" : "RICHARD Cyprien",
    "Year" : "1979",
    "Nation" : "FRA",
    "Run 1" : "1:14.91",
    "Run 2" : "1:11.05",
    "Total Time" : "2:25.96",
    "Diff." : "+1.66",
    "FIS Points" : "10.12",
    "WC Points" : "7.00"
  }, {
    "Rank" : "25",
    "Bib" : "28",
    "FIS Code" : "291768",
    "Name" : "ROBERTO Alessandro",
    "Year" : "1977",
    "Nation" : "ITA",
    "Run 1" : "1:14.66",
    "Run 2" : "1:11.31",
    "Total Time" : "2:25.97",
    "Diff." : "+1.67",
    "FIS Points" : "10.18",
    "WC Points" : "6.00"
  }, {
    "Rank" : "26",
    "Bib" : "44",
    "FIS Code" : "501026",
    "Name" : "RAINER Niklas",
    "Year" : "1983",
    "Nation" : "SWE",
    "Run 1" : "1:14.70",
    "Run 2" : "1:11.46",
    "Total Time" : "2:26.16",
    "Diff." : "+1.86",
    "FIS Points" : "11.34",
    "WC Points" : "5.00"
  }, {
    "Rank" : "27",
    "Bib" : "31",
    "FIS Code" : "500656",
    "Name" : "LARSSON Markus",
    "Year" : "1979",
    "Nation" : "SWE",
    "Run 1" : "1:14.91",
    "Run 2" : "1:11.38",
    "Total Time" : "2:26.29",
    "Diff." : "+1.99",
    "FIS Points" : "12.14",
    "WC Points" : "4.00"
  }, {
    "Rank" : "28",
    "Bib" : "36",
    "FIS Code" : "191227",
    "Name" : "BURTIN Raphael",
    "Year" : "1977",
    "Nation" : "FRA",
    "Run 1" : "1:14.90",
    "Run 2" : "1:13.05",
    "Total Time" : "2:27.95",
    "Diff." : "+3.65",
    "FIS Points" : "22.26",
    "WC Points" : "3.00"
  }, {
    "Rank" : "29",
    "Bib" : "14",
    "FIS Code" : "292250",
    "Name" : "SCHIEPPATI Alberto",
    "Year" : "1981",
    "Nation" : "ITA",
    "Run 1" : "1:14.69",
    "Run 2" : "1:29.17",
    "Total Time" : "2:43.86",
    "Diff." : "+19.56",
    "FIS Points" : "119.28",
    "WC Points" : "0.00"
  }, {
    "Rank" : "Did not qualify for 2nd run"
  }, {
    "Rank" : ""
  }, {
    "Rank" : "",
    "Bib" : "68",
    "FIS Code" : "380260",
    "Name" : "KOSTELIC Ivica",
    "Year" : "1979",
    "Nation" : "CRO",
    "Run 1" : "",
    "Run 2" : "",
    "Total Time" : "",
    "Diff." : "",
    "FIS Points" : "",
    "WC Points" : "0.00"
  }, {
    "Rank" : "",
    "Bib" : "64",
    "FIS Code" : "102271",
    "Name" : "HUDEC Jan",
    "Year" : "1981",
    "Nation" : "CAN",
    "Run 1" : "",
    "Run 2" : "",
    "Total Time" : "",
    "Diff." : "",
    "FIS Points" : "",
    "WC Points" : "0.00"
  }, {
    "Rank" : "",
    "Bib" : "62",
    "FIS Code" : "180532",
    "Name" : "RUOPPA Jonne",
    "Year" : "1987",
    "Nation" : "FIN",
    "Run 1" : "",
    "Run 2" : "",
    "Total Time" : "",
    "Diff." : "",
    "FIS Points" : "",
    "WC Points" : "0.00"
  }, {
    "Rank" : "",
    "Bib" : "60",
    "FIS Code" : "511127",
    "Name" : "GINI Marc",
    "Year" : "1984",
    "Nation" : "SUI",
    "Run 1" : "",
    "Run 2" : "",
    "Total Time" : "",
    "Diff." : "",
    "FIS Points" : "",
    "WC Points" : "0.00"
  }, {
    "Rank" : "",
    "Bib" : "59",
    "FIS Code" : "30149",
    "Name" : "SIMARI BIRKNER Cristian Javier",
    "Year" : "1980",
    "Nation" : "ARG",
    "Run 1" : "",
    "Run 2" : "",
    "Total Time" : "",
    "Diff." : "",
    "FIS Points" : "",
    "WC Points" : "0.00"
  }, {
    "Rank" : "",
    "Bib" : "58",
    "FIS Code" : "293006",
    "Name" : "INNERHOFER Christof",
    "Year" : "1984",
    "Nation" : "ITA",
    "Run 1" : "",
    "Run 2" : "",
    "Total Time" : "",
    "Diff." : "",
    "FIS Points" : "",
    "WC Points" : "0.00"
  }, {
    "Rank" : "",
    "Bib" : "55",
    "FIS Code" : "421483",
    "Name" : "JANSRUD Kjetil",
    "Year" : "1985",
    "Nation" : "NOR",
    "Run 1" : "",
    "Run 2" : "",
    "Total Time" : "",
    "Diff." : "",
    "FIS Points" : "",
    "WC Points" : "0.00"
  }, {
    "Rank" : "",
    "Bib" : "54",
    "FIS Code" : "201702",
    "Name" : "NEUREUTHER Felix",
    "Year" : "1984",
    "Nation" : "GER",
    "Run 1" : "",
    "Run 2" : "",
    "Total Time" : "",
    "Diff." : "",
    "FIS Points" : "",
    "WC Points" : "0.00"
  }, {
    "Rank" : "",
    "Bib" : "53",
    "FIS Code" : "180430",
    "Name" : "RAJALA Jukka",
    "Year" : "1982",
    "Nation" : "FIN",
    "Run 1" : "",
    "Run 2" : "",
    "Total Time" : "",
    "Diff." : "",
    "FIS Points" : "",
    "WC Points" : "0.00"
  }, {
    "Rank" : "",
    "Bib" : "52",
    "FIS Code" : "102635",
    "Name" : "BARRETT Scott",
    "Year" : "1983",
    "Nation" : "CAN",
    "Run 1" : "",
    "Run 2" : "",
    "Total Time" : "",
    "Diff." : "",
    "FIS Points" : "",
    "WC Points" : "0.00"
  }, {
    "Rank" : "",
    "Bib" : "51",
    "FIS Code" : "560425",
    "Name" : "VAJDIC Bernard",
    "Year" : "1980",
    "Nation" : "SLO",
    "Run 1" : "",
    "Run 2" : "",
    "Total Time" : "",
    "Diff." : "",
    "FIS Points" : "",
    "WC Points" : "0.00"
  }, {
    "Rank" : "",
    "Bib" : "50",
    "FIS Code" : "510165",
    "Name" : "HOFER Beni",
    "Year" : "1978",
    "Nation" : "SUI",
    "Run 1" : "",
    "Run 2" : "",
    "Total Time" : "",
    "Diff." : "",
    "FIS Points" : "",
    "WC Points" : "0.00"
  }, {
    "Rank" : "",
    "Bib" : "49",
    "FIS Code" : "190236",
    "Name" : "COVILI Frederic",
    "Year" : "1975",
    "Nation" : "FRA",
    "Run 1" : "",
    "Run 2" : "",
    "Total Time" : "",
    "Diff." : "",
    "FIS Points" : "",
    "WC Points" : "0.00"
  }, {
    "Rank" : "",
    "Bib" : "48",
    "FIS Code" : "150398",
    "Name" : "BANK Ondrej",
    "Year" : "1980",
    "Nation" : "CZE",
    "Run 1" : "",
    "Run 2" : "",
    "Total Time" : "",
    "Diff." : "",
    "FIS Points" : "",
    "WC Points" : "0.00"
  }, {
    "Rank" : "",
    "Bib" : "47",
    "FIS Code" : "534959",
    "Name" : "JITLOFF Tim",
    "Year" : "1985",
    "Nation" : "USA",
    "Run 1" : "",
    "Run 2" : "",
    "Total Time" : "",
    "Diff." : "",
    "FIS Points" : "",
    "WC Points" : "0.00"
  }, {
    "Rank" : "",
    "Bib" : "45",
    "FIS Code" : "533397",
    "Name" : "ZAMANSKY Jake",
    "Year" : "1981",
    "Nation" : "USA",
    "Run 1" : "",
    "Run 2" : "",
    "Total Time" : "",
    "Diff." : "",
    "FIS Points" : "",
    "WC Points" : "0.00"
  }, {
    "Rank" : "",
    "Bib" : "42",
    "FIS Code" : "192653",
    "Name" : "FREY Thomas",
    "Year" : "1984",
    "Nation" : "FRA",
    "Run 1" : "",
    "Run 2" : "",
    "Total Time" : "",
    "Diff." : "",
    "FIS Points" : "",
    "WC Points" : "0.00"
  }, {
    "Rank" : "",
    "Bib" : "41",
    "FIS Code" : "292967",
    "Name" : "EISATH Florian",
    "Year" : "1984",
    "Nation" : "ITA",
    "Run 1" : "",
    "Run 2" : "",
    "Total Time" : "",
    "Diff." : "",
    "FIS Points" : "",
    "WC Points" : "0.00"
  }, {
    "Rank" : "",
    "Bib" : "38",
    "FIS Code" : "51007",
    "Name" : "SCHOERGHOFER Philipp",
    "Year" : "1983",
    "Nation" : "AUT",
    "Run 1" : "",
    "Run 2" : "",
    "Total Time" : "",
    "Diff." : "",
    "FIS Points" : "",
    "WC Points" : "0.00"
  }, {
    "Rank" : "",
    "Bib" : "35",
    "FIS Code" : "533866",
    "Name" : "NYMAN Steven",
    "Year" : "1982",
    "Nation" : "USA",
    "Run 1" : "",
    "Run 2" : "",
    "Total Time" : "",
    "Diff." : "",
    "FIS Points" : "",
    "WC Points" : "0.00"
  }, {
    "Rank" : "",
    "Bib" : "34",
    "FIS Code" : "192665",
    "Name" : "GRANGE Jean-Baptiste",
    "Year" : "1984",
    "Nation" : "FRA",
    "Run 1" : "",
    "Run 2" : "",
    "Total Time" : "",
    "Diff." : "",
    "FIS Points" : "",
    "WC Points" : "0.00"
  }, {
    "Rank" : "",
    "Bib" : "33",
    "FIS Code" : "102263",
    "Name" : "GUAY Erik",
    "Year" : "1981",
    "Nation" : "CAN",
    "Run 1" : "",
    "Run 2" : "",
    "Total Time" : "",
    "Diff." : "",
    "FIS Points" : "",
    "WC Points" : "0.00"
  }, {
    "Rank" : "",
    "Bib" : "32",
    "FIS Code" : "501101",
    "Name" : "BYGGMARK Jens",
    "Year" : "1985",
    "Nation" : "SWE",
    "Run 1" : "",
    "Run 2" : "",
    "Total Time" : "",
    "Diff." : "",
    "FIS Points" : "",
    "WC Points" : "0.00"
  }, {
    "Rank" : "",
    "Bib" : "26",
    "FIS Code" : "50743",
    "Name" : "LANZINGER Matthias",
    "Year" : "1980",
    "Nation" : "AUT",
    "Run 1" : "",
    "Run 2" : "",
    "Total Time" : "",
    "Diff." : "",
    "FIS Points" : "",
    "WC Points" : "0.00"
  }, {
    "Rank" : "",
    "Bib" : "21",
    "FIS Code" : "350032",
    "Name" : "BUECHEL Marco",
    "Year" : "1971",
    "Nation" : "LIE",
    "Run 1" : "",
    "Run 2" : "",
    "Total Time" : "",
    "Diff." : "",
    "FIS Points" : "",
    "WC Points" : "0.00"
  }, {
    "Rank" : "",
    "Bib" : "1",
    "FIS Code" : "532431",
    "Name" : "MILLER Bode",
    "Year" : "1977",
    "Nation" : "USA",
    "Run 1" : "",
    "Run 2" : "",
    "Total Time" : "",
    "Diff." : "",
    "FIS Points" : "",
    "WC Points" : "0.00"
  }, {
    "Rank" : "Did not finish 2nd run"
  }, {
    "Rank" : ""
  }, {
    "Rank" : "",
    "Bib" : "23",
    "FIS Code" : "50547",
    "Name" : "SCHOENFELDER Rainer",
    "Year" : "1977",
    "Nation" : "AUT",
    "Run 1" : "",
    "Run 2" : "",
    "Total Time" : "",
    "Diff." : "",
    "FIS Points" : "",
    "WC Points" : "0.00"
  }, {
    "Rank" : "Did not finish 1st run"
  }, {
    "Rank" : ""
  }, {
    "Rank" : "",
    "Bib" : "67",
    "FIS Code" : "201606",
    "Name" : "KEPPLER Stephan",
    "Year" : "1983",
    "Nation" : "GER",
    "Run 1" : "",
    "Run 2" : "",
    "Total Time" : "",
    "Diff." : "",
    "FIS Points" : "",
    "WC Points" : "0.00"
  }, {
    "Rank" : "",
    "Bib" : "66",
    "FIS Code" : "301312",
    "Name" : "SASAKI Akira",
    "Year" : "1981",
    "Nation" : "JPN",
    "Run 1" : "",
    "Run 2" : "",
    "Total Time" : "",
    "Diff." : "",
    "FIS Points" : "",
    "WC Points" : "0.00"
  }, {
    "Rank" : "",
    "Bib" : "65",
    "FIS Code" : "290998",
    "Name" : "STAUDACHER Patrick",
    "Year" : "1980",
    "Nation" : "ITA",
    "Run 1" : "",
    "Run 2" : "",
    "Total Time" : "",
    "Diff." : "",
    "FIS Points" : "",
    "WC Points" : "0.00"
  }, {
    "Rank" : "",
    "Bib" : "63",
    "FIS Code" : "501076",
    "Name" : "OLSSON Hans",
    "Year" : "1984",
    "Nation" : "SWE",
    "Run 1" : "",
    "Run 2" : "",
    "Total Time" : "",
    "Diff." : "",
    "FIS Points" : "",
    "WC Points" : "0.00"
  }, {
    "Rank" : "",
    "Bib" : "61",
    "FIS Code" : "421400",
    "Name" : "MYHRE Lars Elton",
    "Year" : "1984",
    "Nation" : "NOR",
    "Run 1" : "",
    "Run 2" : "",
    "Total Time" : "",
    "Diff." : "",
    "FIS Points" : "",
    "WC Points" : "0.00"
  }, {
    "Rank" : "",
    "Bib" : "57",
    "FIS Code" : "560355",
    "Name" : "VALENCIC Mitja",
    "Year" : "1978",
    "Nation" : "SLO",
    "Run 1" : "",
    "Run 2" : "",
    "Total Time" : "",
    "Diff." : "",
    "FIS Points" : "",
    "WC Points" : "0.00"
  }, {
    "Rank" : "",
    "Bib" : "56",
    "FIS Code" : "501324",
    "Name" : "OLSSON Matts",
    "Year" : "1988",
    "Nation" : "SWE",
    "Run 1" : "",
    "Run 2" : "",
    "Total Time" : "",
    "Diff." : "",
    "FIS Points" : "",
    "WC Points" : "0.00"
  }, {
    "Rank" : "",
    "Bib" : "46",
    "FIS Code" : "101895",
    "Name" : "ROY Jean-Philippe",
    "Year" : "1979",
    "Nation" : "CAN",
    "Run 1" : "",
    "Run 2" : "",
    "Total Time" : "",
    "Diff." : "",
    "FIS Points" : "",
    "WC Points" : "0.00"
  }, {
    "Rank" : "",
    "Bib" : "37",
    "FIS Code" : "532188",
    "Name" : "SPENCER Dane",
    "Year" : "1977",
    "Nation" : "USA",
    "Run 1" : "",
    "Run 2" : "",
    "Total Time" : "",
    "Diff." : "",
    "FIS Points" : "",
    "WC Points" : "0.00"
  }, {
    "Rank" : "",
    "Bib" : "29",
    "FIS Code" : "192506",
    "Name" : "MISSILLIER Steve",
    "Year" : "1984",
    "Nation" : "FRA",
    "Run 1" : "",
    "Run 2" : "",
    "Total Time" : "",
    "Diff." : "",
    "FIS Points" : "",
    "WC Points" : "0.00"
  }, {
    "Rank" : "",
    "Bib" : "8",
    "FIS Code" : "510727",
    "Name" : "DEFAGO Didier",
    "Year" : "1977",
    "Nation" : "SUI",
    "Run 1" : "",
    "Run 2" : "",
    "Total Time" : "",
    "Diff." : "",
    "FIS Points" : "",
    "WC Points" : "0.00"
  }, {
    "Rank" : "",
    "Bib" : "5",
    "FIS Code" : "180251",
    "Name" : "PALANDER Kalle",
    "Year" : "1977",
    "Nation" : "FIN",
    "Run 1" : "",
    "Run 2" : "",
    "Total Time" : "",
    "Diff." : "",
    "FIS Points" : "",
    "WC Points" : "0.00"
  }, {
    "Rank" : ""
  } ]
}