{
  "result" : [ {
    "Rank" : "1",
    "Bib" : "23",
    "FIS Code" : "102271",
    "Name" : "HUDEC Jan",
    "Year" : "1981",
    "Nation" : "CAN",
    "Total Time" : "0.00",
    "Diff." : ""
  }, {
    "Rank" : "2",
    "Bib" : "2",
    "FIS Code" : "50753",
    "Name" : "KROELL Klaus",
    "Year" : "1980",
    "Nation" : "AUT",
    "Total Time" : "0.00",
    "Diff." : "+0.08"
  }, {
    "Rank" : "3",
    "Bib" : "5",
    "FIS Code" : "532431",
    "Name" : "MILLER Bode",
    "Year" : "1977",
    "Nation" : "USA",
    "Total Time" : "0.00",
    "Diff." : "+0.10"
  }, {
    "Rank" : "4",
    "Bib" : "18",
    "FIS Code" : "510030",
    "Name" : "CUCHE Didier",
    "Year" : "1974",
    "Nation" : "SUI",
    "Total Time" : "0.00",
    "Diff." : "+0.12"
  }, {
    "Rank" : "5",
    "Bib" : "16",
    "FIS Code" : "50041",
    "Name" : "WALCHHOFER Michael",
    "Year" : "1975",
    "Nation" : "AUT",
    "Total Time" : "0.00",
    "Diff." : "+0.15"
  }, {
    "Rank" : "6",
    "Bib" : "1",
    "FIS Code" : "291641",
    "Name" : "SULZENBACHER Kurt",
    "Year" : "1976",
    "Nation" : "ITA",
    "Total Time" : "0.00",
    "Diff." : "+0.21"
  }, {
    "Rank" : "7",
    "Bib" : "13",
    "FIS Code" : "533866",
    "Name" : "NYMAN Steven",
    "Year" : "1982",
    "Nation" : "USA",
    "Total Time" : "0.00",
    "Diff." : "+0.36"
  }, {
    "Rank" : "8",
    "Bib" : "11",
    "FIS Code" : "560332",
    "Name" : "JERMAN Andrej",
    "Year" : "1978",
    "Nation" : "SLO",
    "Total Time" : "0.00",
    "Diff." : "+0.40"
  }, {
    "Rank" : "9",
    "Bib" : "6",
    "FIS Code" : "50423",
    "Name" : "MAIER Hermann",
    "Year" : "1972",
    "Nation" : "AUT",
    "Total Time" : "0.00",
    "Diff." : "+0.41"
  }, {
    "Rank" : "10",
    "Bib" : "43",
    "FIS Code" : "102873",
    "Name" : "KUCERA John",
    "Year" : "1984",
    "Nation" : "CAN",
    "Total Time" : "0.00",
    "Diff." : "+0.43"
  }, {
    "Rank" : "11",
    "Bib" : "30",
    "FIS Code" : "533131",
    "Name" : "SULLIVAN Marco",
    "Year" : "1980",
    "Nation" : "USA",
    "Total Time" : "0.00",
    "Diff." : "+0.45"
  }, {
    "Rank" : "12",
    "Bib" : "14",
    "FIS Code" : "532490",
    "Name" : "MACARTNEY Scott",
    "Year" : "1978",
    "Nation" : "USA",
    "Total Time" : "0.00",
    "Diff." : "+0.48"
  }, {
    "Rank" : "13",
    "Bib" : "21",
    "FIS Code" : "350032",
    "Name" : "BUECHEL Marco",
    "Year" : "1971",
    "Nation" : "LIE",
    "Total Time" : "0.00",
    "Diff." : "+0.49"
  }, {
    "Rank" : "14",
    "Bib" : "19",
    "FIS Code" : "102263",
    "Name" : "GUAY Erik",
    "Year" : "1981",
    "Nation" : "CAN",
    "Total Time" : "0.00",
    "Diff." : "+0.52"
  }, {
    "Rank" : "15",
    "Bib" : "12",
    "FIS Code" : "510767",
    "Name" : "HOFFMANN Ambrosi",
    "Year" : "1977",
    "Nation" : "SUI",
    "Total Time" : "0.00",
    "Diff." : "+0.54"
  }, {
    "Rank" : "16",
    "Bib" : "20",
    "FIS Code" : "421328",
    "Name" : "SVINDAL Aksel Lund",
    "Year" : "1982",
    "Nation" : "NOR",
    "Total Time" : "0.00",
    "Diff." : "+0.63"
  }, {
    "Rank" : "17",
    "Bib" : "24",
    "FIS Code" : "191591",
    "Name" : "BERTRAND Yannick",
    "Year" : "1980",
    "Nation" : "FRA",
    "Total Time" : "0.00",
    "Diff." : "+0.64"
  }, {
    "Rank" : "18",
    "Bib" : "8",
    "FIS Code" : "102899",
    "Name" : "OSBORNE-PARADIS Manuel",
    "Year" : "1984",
    "Nation" : "CAN",
    "Total Time" : "0.00",
    "Diff." : "+0.75"
  }, {
    "Rank" : "19",
    "Bib" : "28",
    "FIS Code" : "191740",
    "Name" : "CLAREY Johan",
    "Year" : "1981",
    "Nation" : "FRA",
    "Total Time" : "0.00",
    "Diff." : "+0.80"
  }, {
    "Rank" : "20",
    "Bib" : "65",
    "FIS Code" : "293006",
    "Name" : "INNERHOFER Christof",
    "Year" : "1984",
    "Nation" : "ITA",
    "Total Time" : "0.00",
    "Diff." : "+0.82"
  }, {
    "Rank" : "21",
    "Bib" : "54",
    "FIS Code" : "510498",
    "Name" : "ZUEGER Cornel",
    "Year" : "1981",
    "Nation" : "SUI",
    "Total Time" : "0.00",
    "Diff." : "+0.87"
  }, {
    "Rank" : "21",
    "Bib" : "22",
    "FIS Code" : "510727",
    "Name" : "DEFAGO Didier",
    "Year" : "1977",
    "Nation" : "SUI",
    "Total Time" : "0.00",
    "Diff." : "+0.87"
  }, {
    "Rank" : "23",
    "Bib" : "34",
    "FIS Code" : "50858",
    "Name" : "STREITBERGER Georg",
    "Year" : "1981",
    "Nation" : "AUT",
    "Total Time" : "0.00",
    "Diff." : "+0.90"
  }, {
    "Rank" : "24",
    "Bib" : "48",
    "FIS Code" : "191911",
    "Name" : "NOCENTI Cyril",
    "Year" : "1982",
    "Nation" : "FRA",
    "Total Time" : "0.00",
    "Diff." : "+0.91"
  }, {
    "Rank" : "25",
    "Bib" : "70",
    "FIS Code" : "534567",
    "Name" : "LANNING Thomas (tj)",
    "Year" : "1984",
    "Nation" : "USA",
    "Total Time" : "0.00",
    "Diff." : "+0.92"
  }, {
    "Rank" : "26",
    "Bib" : "46",
    "FIS Code" : "190930",
    "Name" : "DENERIAZ Antoine",
    "Year" : "1976",
    "Nation" : "FRA",
    "Total Time" : "0.00",
    "Diff." : "+0.94"
  }, {
    "Rank" : "27",
    "Bib" : "38",
    "FIS Code" : "501076",
    "Name" : "OLSSON Hans",
    "Year" : "1984",
    "Nation" : "SWE",
    "Total Time" : "0.00",
    "Diff." : "+1.01"
  }, {
    "Rank" : "28",
    "Bib" : "9",
    "FIS Code" : "191116",
    "Name" : "DALCIN Pierre-Emmanuel",
    "Year" : "1977",
    "Nation" : "FRA",
    "Total Time" : "0.00",
    "Diff." : "+1.14"
  }, {
    "Rank" : "29",
    "Bib" : "67",
    "FIS Code" : "50742",
    "Name" : "REICHELT Hannes",
    "Year" : "1980",
    "Nation" : "AUT",
    "Total Time" : "0.00",
    "Diff." : "+1.19"
  }, {
    "Rank" : "30",
    "Bib" : "29",
    "FIS Code" : "292514",
    "Name" : "HEEL Werner",
    "Year" : "1982",
    "Nation" : "ITA",
    "Total Time" : "0.00",
    "Diff." : "+1.20"
  }, {
    "Rank" : "31",
    "Bib" : "7",
    "FIS Code" : "50625",
    "Name" : "RAICH Benjamin",
    "Year" : "1978",
    "Nation" : "AUT",
    "Total Time" : "0.00",
    "Diff." : "+1.24"
  }, {
    "Rank" : "32",
    "Bib" : "25",
    "FIS Code" : "50695",
    "Name" : "BUDER Andreas",
    "Year" : "1979",
    "Nation" : "AUT",
    "Total Time" : "0.00",
    "Diff." : "+1.28"
  }, {
    "Rank" : "33",
    "Bib" : "76",
    "FIS Code" : "102961",
    "Name" : "DIXON Robbie",
    "Year" : "1985",
    "Nation" : "CAN",
    "Total Time" : "0.00",
    "Diff." : "+1.29"
  }, {
    "Rank" : "34",
    "Bib" : "66",
    "FIS Code" : "510207",
    "Name" : "HARI Konrad",
    "Year" : "1978",
    "Nation" : "SUI",
    "Total Time" : "0.00",
    "Diff." : "+1.32"
  }, {
    "Rank" : "35",
    "Bib" : "50",
    "FIS Code" : "421400",
    "Name" : "MYHRE Lars Elton",
    "Year" : "1984",
    "Nation" : "NOR",
    "Total Time" : "0.00",
    "Diff." : "+1.37"
  }, {
    "Rank" : "36",
    "Bib" : "15",
    "FIS Code" : "50451",
    "Name" : "GRUBER Christoph",
    "Year" : "1976",
    "Nation" : "AUT",
    "Total Time" : "0.00",
    "Diff." : "+1.38"
  }, {
    "Rank" : "36",
    "Bib" : "3",
    "FIS Code" : "510747",
    "Name" : "GRUENENFELDER Tobias",
    "Year" : "1977",
    "Nation" : "SUI",
    "Total Time" : "0.00",
    "Diff." : "+1.38"
  }, {
    "Rank" : "38",
    "Bib" : "42",
    "FIS Code" : "510165",
    "Name" : "HOFER Beni",
    "Year" : "1978",
    "Nation" : "SUI",
    "Total Time" : "0.00",
    "Diff." : "+1.39"
  }, {
    "Rank" : "39",
    "Bib" : "47",
    "FIS Code" : "201606",
    "Name" : "KEPPLER Stephan",
    "Year" : "1983",
    "Nation" : "GER",
    "Total Time" : "0.00",
    "Diff." : "+1.43"
  }, {
    "Rank" : "40",
    "Bib" : "78",
    "FIS Code" : "201987",
    "Name" : "STRODL Andreas",
    "Year" : "1987",
    "Nation" : "GER",
    "Total Time" : "0.00",
    "Diff." : "+1.44"
  }, {
    "Rank" : "41",
    "Bib" : "72",
    "FIS Code" : "380292",
    "Name" : "ZRNCIC-DIM Natko",
    "Year" : "1986",
    "Nation" : "CRO",
    "Total Time" : "0.00",
    "Diff." : "+1.48"
  }, {
    "Rank" : "42",
    "Bib" : "10",
    "FIS Code" : "51005",
    "Name" : "SCHEIBER Mario",
    "Year" : "1983",
    "Nation" : "AUT",
    "Total Time" : "0.00",
    "Diff." : "+1.55"
  }, {
    "Rank" : "43",
    "Bib" : "69",
    "FIS Code" : "201542",
    "Name" : "STRODL Peter",
    "Year" : "1982",
    "Nation" : "GER",
    "Total Time" : "0.00",
    "Diff." : "+1.59"
  }, {
    "Rank" : "44",
    "Bib" : "17",
    "FIS Code" : "292455",
    "Name" : "FILL Peter",
    "Year" : "1982",
    "Nation" : "ITA",
    "Total Time" : "0.00",
    "Diff." : "+1.60"
  }, {
    "Rank" : "45",
    "Bib" : "77",
    "FIS Code" : "533842",
    "Name" : "FRANCIS Kevin",
    "Year" : "1982",
    "Nation" : "USA",
    "Total Time" : "0.00",
    "Diff." : "+1.61"
  }, {
    "Rank" : "45",
    "Bib" : "58",
    "FIS Code" : "292291",
    "Name" : "THANEI Stefan",
    "Year" : "1981",
    "Nation" : "ITA",
    "Total Time" : "0.00",
    "Diff." : "+1.61"
  }, {
    "Rank" : "47",
    "Bib" : "27",
    "FIS Code" : "290998",
    "Name" : "STAUDACHER Patrick",
    "Year" : "1980",
    "Nation" : "ITA",
    "Total Time" : "0.00",
    "Diff." : "+1.67"
  }, {
    "Rank" : "48",
    "Bib" : "44",
    "FIS Code" : "102814",
    "Name" : "BOURQUE Francois",
    "Year" : "1984",
    "Nation" : "CAN",
    "Total Time" : "0.00",
    "Diff." : "+1.71"
  }, {
    "Rank" : "49",
    "Bib" : "57",
    "FIS Code" : "50761",
    "Name" : "ALSTER Christoph",
    "Year" : "1980",
    "Nation" : "AUT",
    "Total Time" : "0.00",
    "Diff." : "+1.76"
  }, {
    "Rank" : "50",
    "Bib" : "55",
    "FIS Code" : "534939",
    "Name" : "FISHER Erik",
    "Year" : "1985",
    "Nation" : "USA",
    "Total Time" : "0.00",
    "Diff." : "+1.82"
  }, {
    "Rank" : "51",
    "Bib" : "40",
    "FIS Code" : "291399",
    "Name" : "GIRARDI Walter",
    "Year" : "1976",
    "Nation" : "ITA",
    "Total Time" : "0.00",
    "Diff." : "+1.86"
  }, {
    "Rank" : "52",
    "Bib" : "71",
    "FIS Code" : "380260",
    "Name" : "KOSTELIC Ivica",
    "Year" : "1979",
    "Nation" : "CRO",
    "Total Time" : "0.00",
    "Diff." : "+1.87"
  }, {
    "Rank" : "52",
    "Bib" : "4",
    "FIS Code" : "510890",
    "Name" : "ZURBRIGGEN Silvan",
    "Year" : "1981",
    "Nation" : "SUI",
    "Total Time" : "0.00",
    "Diff." : "+1.87"
  }, {
    "Rank" : "54",
    "Bib" : "52",
    "FIS Code" : "291389",
    "Name" : "FISCHNALLER Roland",
    "Year" : "1975",
    "Nation" : "ITA",
    "Total Time" : "0.00",
    "Diff." : "+1.91"
  }, {
    "Rank" : "54",
    "Bib" : "36",
    "FIS Code" : "192746",
    "Name" : "THEAUX Adrien",
    "Year" : "1984",
    "Nation" : "FRA",
    "Total Time" : "0.00",
    "Diff." : "+1.91"
  }, {
    "Rank" : "56",
    "Bib" : "26",
    "FIS Code" : "191415",
    "Name" : "BOTTOLLIER-LASQUIN Marc",
    "Year" : "1979",
    "Nation" : "FRA",
    "Total Time" : "0.00",
    "Diff." : "+1.92"
  }, {
    "Rank" : "57",
    "Bib" : "31",
    "FIS Code" : "50833",
    "Name" : "GRUGGER Hans",
    "Year" : "1981",
    "Nation" : "AUT",
    "Total Time" : "0.00",
    "Diff." : "+1.98"
  }, {
    "Rank" : "58",
    "Bib" : "63",
    "FIS Code" : "201439",
    "Name" : "STEHLE Johannes",
    "Year" : "1981",
    "Nation" : "GER",
    "Total Time" : "0.00",
    "Diff." : "+2.00"
  }, {
    "Rank" : "59",
    "Bib" : "37",
    "FIS Code" : "191964",
    "Name" : "POISSON David",
    "Year" : "1982",
    "Nation" : "FRA",
    "Total Time" : "0.00",
    "Diff." : "+2.04"
  }, {
    "Rank" : "60",
    "Bib" : "75",
    "FIS Code" : "510307",
    "Name" : "BRAND Olivier",
    "Year" : "1980",
    "Nation" : "SUI",
    "Total Time" : "0.00",
    "Diff." : "+2.05"
  }, {
    "Rank" : "61",
    "Bib" : "41",
    "FIS Code" : "561067",
    "Name" : "PERKO Rok",
    "Year" : "1985",
    "Nation" : "SLO",
    "Total Time" : "0.00",
    "Diff." : "+2.10"
  }, {
    "Rank" : "62",
    "Bib" : "60",
    "FIS Code" : "293141",
    "Name" : "VARETTONI Silvano",
    "Year" : "1984",
    "Nation" : "ITA",
    "Total Time" : "0.00",
    "Diff." : "+2.11"
  }, {
    "Rank" : "63",
    "Bib" : "74",
    "FIS Code" : "420911",
    "Name" : "SOLBAKKEN Bjarne",
    "Year" : "1977",
    "Nation" : "NOR",
    "Total Time" : "0.00",
    "Diff." : "+2.20"
  }, {
    "Rank" : "64",
    "Bib" : "53",
    "FIS Code" : "40171",
    "Name" : "BRANCH Craig",
    "Year" : "1977",
    "Nation" : "AUS",
    "Total Time" : "0.00",
    "Diff." : "+2.21"
  }, {
    "Rank" : "65",
    "Bib" : "45",
    "FIS Code" : "192932",
    "Name" : "FAYED Guillermo",
    "Year" : "1985",
    "Nation" : "FRA",
    "Total Time" : "0.00",
    "Diff." : "+2.34"
  }, {
    "Rank" : "66",
    "Bib" : "39",
    "FIS Code" : "533098",
    "Name" : "FRIEDMAN Bryon",
    "Year" : "1980",
    "Nation" : "USA",
    "Total Time" : "0.00",
    "Diff." : "+2.38"
  }, {
    "Rank" : "67",
    "Bib" : "56",
    "FIS Code" : "510969",
    "Name" : "BONETTI Michael",
    "Year" : "1982",
    "Nation" : "SUI",
    "Total Time" : "0.00",
    "Diff." : "+2.44"
  }, {
    "Rank" : "68",
    "Bib" : "32",
    "FIS Code" : "292491",
    "Name" : "MOELGG Manfred",
    "Year" : "1982",
    "Nation" : "ITA",
    "Total Time" : "0.00",
    "Diff." : "+2.47"
  }, {
    "Rank" : "69",
    "Bib" : "62",
    "FIS Code" : "150398",
    "Name" : "BANK Ondrej",
    "Year" : "1980",
    "Nation" : "CZE",
    "Total Time" : "0.00",
    "Diff." : "+2.50"
  }, {
    "Rank" : "70",
    "Bib" : "80",
    "FIS Code" : "40255",
    "Name" : "BRAUER Jono",
    "Year" : "1981",
    "Nation" : "AUS",
    "Total Time" : "0.00",
    "Diff." : "+2.52"
  }, {
    "Rank" : "71",
    "Bib" : "51",
    "FIS Code" : "191462",
    "Name" : "PAQUIN Pierre",
    "Year" : "1979",
    "Nation" : "FRA",
    "Total Time" : "0.00",
    "Diff." : "+2.61"
  }, {
    "Rank" : "72",
    "Bib" : "59",
    "FIS Code" : "102947",
    "Name" : "SINE Gareth",
    "Year" : "1985",
    "Nation" : "CAN",
    "Total Time" : "0.00",
    "Diff." : "+2.83"
  }, {
    "Rank" : "73",
    "Bib" : "73",
    "FIS Code" : "510434",
    "Name" : "MATTI Bernhard",
    "Year" : "1981",
    "Nation" : "SUI",
    "Total Time" : "0.00",
    "Diff." : "+2.85"
  }, {
    "Rank" : "74",
    "Bib" : "49",
    "FIS Code" : "220228",
    "Name" : "MICKEL Finlay",
    "Year" : "1977",
    "Nation" : "GBR",
    "Total Time" : "0.00",
    "Diff." : "+2.88"
  }, {
    "Rank" : "75",
    "Bib" : "81",
    "FIS Code" : "501324",
    "Name" : "OLSSON Matts",
    "Year" : "1988",
    "Nation" : "SWE",
    "Total Time" : "0.00",
    "Diff." : "+2.94"
  }, {
    "Rank" : "76",
    "Bib" : "82",
    "FIS Code" : "103106",
    "Name" : "LEMAN Brady",
    "Year" : "1986",
    "Nation" : "CAN",
    "Total Time" : "0.00",
    "Diff." : "+2.96"
  }, {
    "Rank" : "77",
    "Bib" : "33",
    "FIS Code" : "560447",
    "Name" : "SPORN Andrej",
    "Year" : "1981",
    "Nation" : "SLO",
    "Total Time" : "0.00",
    "Diff." : "+3.42"
  }, {
    "Rank" : "78",
    "Bib" : "86",
    "FIS Code" : "380298",
    "Name" : "SIROKI Tin",
    "Year" : "1987",
    "Nation" : "CRO",
    "Total Time" : "0.00",
    "Diff." : "+3.50"
  }, {
    "Rank" : "79",
    "Bib" : "79",
    "FIS Code" : "103090",
    "Name" : "HELIE Louis-Pierre",
    "Year" : "1986",
    "Nation" : "CAN",
    "Total Time" : "0.00",
    "Diff." : "+4.79"
  }, {
    "Rank" : "80",
    "Bib" : "85",
    "FIS Code" : "292000",
    "Name" : "BLARDONE Massimiliano",
    "Year" : "1979",
    "Nation" : "ITA",
    "Total Time" : "0.00",
    "Diff." : "+5.15"
  }, {
    "Rank" : "81",
    "Bib" : "87",
    "FIS Code" : "40324",
    "Name" : "FETTERPLACE Brenton",
    "Year" : "1985",
    "Nation" : "AUS",
    "Total Time" : "0.00",
    "Diff." : "+7.05"
  }, {
    "Rank" : "82",
    "Bib" : "83",
    "FIS Code" : "220083",
    "Name" : "BAXTER Noel",
    "Year" : "1981",
    "Nation" : "GBR",
    "Total Time" : "0.00",
    "Diff." : "+7.48"
  }, {
    "Rank" : "83",
    "Bib" : "84",
    "FIS Code" : "410252",
    "Name" : "BRIDGWATER Mark",
    "Year" : "1985",
    "Nation" : "NZL",
    "Total Time" : "0.00",
    "Diff." : "+8.69"
  }, {
    "Rank" : "Disqualified 1st run"
  }, {
    "Rank" : ""
  }, {
    "Rank" : "",
    "Bib" : "68",
    "FIS Code" : "501026",
    "Name" : "RAINER Niklas",
    "Year" : "1983",
    "Nation" : "SWE",
    "Total Time" : "0.00",
    "Diff." : ""
  }, {
    "Rank" : "",
    "Bib" : "64",
    "FIS Code" : "50919",
    "Name" : "STRUGER Peter",
    "Year" : "1982",
    "Nation" : "AUT",
    "Total Time" : "0.00",
    "Diff." : ""
  }, {
    "Rank" : "",
    "Bib" : "35",
    "FIS Code" : "51215",
    "Name" : "BAUMANN Romed",
    "Year" : "1986",
    "Nation" : "AUT",
    "Total Time" : "0.00",
    "Diff." : ""
  }, {
    "Rank" : "Did not finish 1st run"
  }, {
    "Rank" : ""
  }, {
    "Rank" : "",
    "Bib" : "61",
    "FIS Code" : "530939",
    "Name" : "WEIBRECHT Andrew",
    "Year" : "1986",
    "Nation" : "USA",
    "Total Time" : "0.00",
    "Diff." : ""
  }, {
    "Rank" : ""
  } ]
}