{
  "raceInfo" : {
    "Jury" : {
      "TD FIS" : {
        "name" : "",
        "country" : ""
      },
      "Referee" : {
        "name" : "",
        "country" : ""
      },
      "Chief of Race" : {
        "name" : "",
        "country" : ""
      }
    },
    "Technical Data" : {
      "Start Altitude" : "m.",
      "Finish Altitude" : "m.",
      "Vertical Drop" : "0 m.",
      "Homologation Number" : ""
    }
  },
  "results" : [ {
    "Rank" : "1",
    "Bib" : "",
    "FIS Code" : "-10823",
    "Name" : "NIERLICH Rudolf",
    "Year" : "1966",
    "Nation" : "AUT",
    "Run 1" : "",
    "Run 2" : "",
    "Total Time" : "1:32.32",
    "Diff." : "",
    "FIS Points" : "0.00"
  }, {
    "Rank" : "2",
    "Bib" : "",
    "FIS Code" : "420059",
    "Name" : "FURUSETH Ole Christian",
    "Year" : "1967",
    "Nation" : "NOR",
    "Run 1" : "",
    "Run 2" : "",
    "Total Time" : "1:32.61",
    "Diff." : "+0.29",
    "FIS Points" : "0.00"
  }, {
    "Rank" : "3",
    "Bib" : "",
    "FIS Code" : "200028",
    "Name" : "BITTNER Armin",
    "Year" : "1964",
    "Nation" : "GER",
    "Run 1" : "",
    "Run 2" : "",
    "Total Time" : "1:32.69",
    "Diff." : "+0.37",
    "FIS Points" : "0.00"
  }, {
    "Rank" : "4",
    "Bib" : "",
    "FIS Code" : "290539",
    "Name" : "TOMBA Alberto",
    "Year" : "1966",
    "Nation" : "ITA",
    "Run 1" : "",
    "Run 2" : "",
    "Total Time" : "1:32.91",
    "Diff." : "+0.59",
    "FIS Points" : "0.00"
  }, {
    "Rank" : "5",
    "Bib" : "",
    "FIS Code" : "-10764",
    "Name" : "ZURBRIGGEN Pirmin",
    "Year" : "1963",
    "Nation" : "SUI",
    "Run 1" : "",
    "Run 2" : "",
    "Total Time" : "1:33.08",
    "Diff." : "+0.76",
    "FIS Points" : "0.00"
  }, {
    "Rank" : "6",
    "Bib" : "",
    "FIS Code" : "-10456",
    "Name" : "NILSSON Jonas",
    "Year" : "1963",
    "Nation" : "SWE",
    "Run 1" : "",
    "Run 2" : "",
    "Total Time" : "1:33.18",
    "Diff." : "+0.86",
    "FIS Points" : "0.00"
  }, {
    "Rank" : "7",
    "Bib" : "",
    "FIS Code" : "50127",
    "Name" : "MADER Guenther",
    "Year" : "1964",
    "Nation" : "AUT",
    "Run 1" : "",
    "Run 2" : "",
    "Total Time" : "1:33.30",
    "Diff." : "+0.98",
    "FIS Points" : "0.00"
  }, {
    "Rank" : "8",
    "Bib" : "",
    "FIS Code" : "200271",
    "Name" : "ROTH Peter",
    "Year" : "1961",
    "Nation" : "GER",
    "Run 1" : "",
    "Run 2" : "",
    "Total Time" : "1:34.00",
    "Diff." : "+1.68",
    "FIS Points" : "0.00"
  }, {
    "Rank" : "9",
    "Bib" : "",
    "FIS Code" : "-10724",
    "Name" : "FROMMELT Paul",
    "Year" : "1957",
    "Nation" : "LIE",
    "Run 1" : "",
    "Run 2" : "",
    "Total Time" : "1:34.15",
    "Diff." : "+1.83",
    "FIS Points" : "0.00"
  }, {
    "Rank" : "10",
    "Bib" : "",
    "FIS Code" : "50222",
    "Name" : "TRITSCHER Michael",
    "Year" : "1965",
    "Nation" : "AUT",
    "Run 1" : "",
    "Run 2" : "",
    "Total Time" : "1:34.31",
    "Diff." : "+1.99",
    "FIS Points" : "0.00"
  }, {
    "Rank" : "11",
    "Bib" : "",
    "FIS Code" : "290435",
    "Name" : "PRAMOTTON Richard",
    "Year" : "1964",
    "Nation" : "ITA",
    "Run 1" : "",
    "Run 2" : "",
    "Total Time" : "1:34.73",
    "Diff." : "+2.41",
    "FIS Points" : "0.00"
  }, {
    "Rank" : "12",
    "Bib" : "",
    "FIS Code" : "-10275",
    "Name" : "MCGRATH Felix",
    "Year" : "",
    "Nation" : "USA",
    "Run 1" : "",
    "Run 2" : "",
    "Total Time" : "1:35.19",
    "Diff." : "+2.87",
    "FIS Points" : "0.00"
  }, {
    "Rank" : "13",
    "Bib" : "",
    "FIS Code" : "190096",
    "Name" : "CRETIER Jean-Luc",
    "Year" : "1966",
    "Nation" : "FRA",
    "Run 1" : "",
    "Run 2" : "",
    "Total Time" : "1:35.26",
    "Diff." : "+2.94",
    "FIS Points" : "0.00"
  }, {
    "Rank" : "14",
    "Bib" : "",
    "FIS Code" : "290274",
    "Name" : "GRIGIS Roberto",
    "Year" : "1962",
    "Nation" : "ITA",
    "Run 1" : "",
    "Run 2" : "",
    "Total Time" : "1:35.57",
    "Diff." : "+3.25",
    "FIS Points" : "0.00"
  }, {
    "Rank" : "15",
    "Bib" : "",
    "FIS Code" : "310064",
    "Name" : "PETROVIC Rok",
    "Year" : "1966",
    "Nation" : "JUG",
    "Run 1" : "",
    "Run 2" : "",
    "Total Time" : "1:35.74",
    "Diff." : "+3.42",
    "FIS Points" : "0.00"
  }, {
    "Rank" : ""
  } ],
  "eventInfo" : {
    "Date" : "10.03.1989",
    "Place" : "Shigakogen",
    "Nation" : "JPN",
    "Codex" : "1705",
    "Discipline" : "Slalom",
    "Gender" : "M",
    "Category" : "WC",
    "Comments" : "",
    "Down load" : ""
  }
}