{
  "result" : [ {
    "Rank" : "1",
    "Bib" : "3",
    "FIS Code" : "295342",
    "Name" : "PUTZER Karen",
    "Year" : "1978",
    "Nation" : "ITA",
    "Run 1" : "1:12.75",
    "Run 2" : "1:14.80",
    "Total Time" : "2:27.55",
    "Diff." : "",
    "FIS Points" : "0.00",
    "WC Points" : "0.00"
  }, {
    "Rank" : "2",
    "Bib" : "9",
    "FIS Code" : "295445",
    "Name" : "KARBON Denise",
    "Year" : "1980",
    "Nation" : "ITA",
    "Run 1" : "1:13.85",
    "Run 2" : "1:14.73",
    "Total Time" : "2:28.58",
    "Diff." : "+1.03",
    "FIS Points" : "6.00",
    "WC Points" : "0.00"
  }, {
    "Rank" : "3",
    "Bib" : "5",
    "FIS Code" : "55690",
    "Name" : "HOSP Nicole",
    "Year" : "1983",
    "Nation" : "AUT",
    "Run 1" : "1:13.13",
    "Run 2" : "1:15.75",
    "Total Time" : "2:28.88",
    "Diff." : "+1.33",
    "FIS Points" : "7.75",
    "WC Points" : "0.00"
  }, {
    "Rank" : "4",
    "Bib" : "8",
    "FIS Code" : "205378",
    "Name" : "ERTL Martina",
    "Year" : "1973",
    "Nation" : "GER",
    "Run 1" : "1:13.37",
    "Run 2" : "1:15.58",
    "Total Time" : "2:28.95",
    "Diff." : "+1.40",
    "FIS Points" : "8.16",
    "WC Points" : "0.00"
  }, {
    "Rank" : "5",
    "Bib" : "7",
    "FIS Code" : "505483",
    "Name" : "PAERSON Anja",
    "Year" : "1981",
    "Nation" : "SWE",
    "Run 1" : "1:14.44",
    "Run 2" : "1:14.88",
    "Total Time" : "2:29.32",
    "Diff." : "+1.77",
    "FIS Points" : "10.32",
    "WC Points" : "0.00"
  }, {
    "Rank" : "6",
    "Bib" : "11",
    "FIS Code" : "425001",
    "Name" : "FLEMMEN Andrine",
    "Year" : "1974",
    "Nation" : "NOR",
    "Run 1" : "1:13.45",
    "Run 2" : "1:15.92",
    "Total Time" : "2:29.37",
    "Diff." : "+1.82",
    "FIS Points" : "10.61",
    "WC Points" : "0.00"
  }, {
    "Rank" : "7",
    "Bib" : "23",
    "FIS Code" : "536481",
    "Name" : "SCHLEPER Sarah",
    "Year" : "1979",
    "Nation" : "USA",
    "Run 1" : "1:14.30",
    "Run 2" : "1:15.40",
    "Total Time" : "2:29.70",
    "Diff." : "+2.15",
    "FIS Points" : "12.53",
    "WC Points" : "0.00"
  }, {
    "Rank" : "8",
    "Bib" : "18",
    "FIS Code" : "55313",
    "Name" : "ROHREGGER Eveline",
    "Year" : "1977",
    "Nation" : "AUT",
    "Run 1" : "1:14.08",
    "Run 2" : "1:15.71",
    "Total Time" : "2:29.79",
    "Diff." : "+2.24",
    "FIS Points" : "13.06",
    "WC Points" : "0.00"
  }, {
    "Rank" : "9",
    "Bib" : "20",
    "FIS Code" : "105741",
    "Name" : "FORSYTH Allison",
    "Year" : "1978",
    "Nation" : "CAN",
    "Run 1" : "1:14.41",
    "Run 2" : "1:16.10",
    "Total Time" : "2:30.51",
    "Diff." : "+2.96",
    "FIS Points" : "17.25",
    "WC Points" : "0.00"
  }, {
    "Rank" : "10",
    "Bib" : "21",
    "FIS Code" : "55539",
    "Name" : "BERGER Silvia",
    "Year" : "1980",
    "Nation" : "AUT",
    "Run 1" : "1:14.58",
    "Run 2" : "1:15.96",
    "Total Time" : "2:30.54",
    "Diff." : "+2.99",
    "FIS Points" : "17.43",
    "WC Points" : "0.00"
  }, {
    "Rank" : "11",
    "Bib" : "4",
    "FIS Code" : "55212",
    "Name" : "MEISSNITZER Alexandra",
    "Year" : "1973",
    "Nation" : "AUT",
    "Run 1" : "1:14.71",
    "Run 2" : "1:15.96",
    "Total Time" : "2:30.67",
    "Diff." : "+3.12",
    "FIS Points" : "18.19",
    "WC Points" : "0.00"
  }, {
    "Rank" : "12",
    "Bib" : "15",
    "FIS Code" : "565243",
    "Name" : "MAZE Tina",
    "Year" : "1983",
    "Nation" : "SLO",
    "Run 1" : "1:14.94",
    "Run 2" : "1:15.82",
    "Total Time" : "2:30.76",
    "Diff." : "+3.21",
    "FIS Points" : "18.71",
    "WC Points" : "0.00"
  }, {
    "Rank" : "13",
    "Bib" : "19",
    "FIS Code" : "425389",
    "Name" : "NILSEN Stina Hofgard",
    "Year" : "1979",
    "Nation" : "NOR",
    "Run 1" : "1:15.34",
    "Run 2" : "1:15.45",
    "Total Time" : "2:30.79",
    "Diff." : "+3.24",
    "FIS Points" : "18.88",
    "WC Points" : "0.00"
  }, {
    "Rank" : "14",
    "Bib" : "17",
    "FIS Code" : "536138",
    "Name" : "CLARK Kirsten L",
    "Year" : "1977",
    "Nation" : "USA",
    "Run 1" : "1:15.56",
    "Run 2" : "1:15.51",
    "Total Time" : "2:31.07",
    "Diff." : "+3.52",
    "FIS Points" : "20.52",
    "WC Points" : "0.00"
  }, {
    "Rank" : "15",
    "Bib" : "12",
    "FIS Code" : "505187",
    "Name" : "OTTOSSON Anna",
    "Year" : "1976",
    "Nation" : "SWE",
    "Run 1" : "1:15.01",
    "Run 2" : "1:16.27",
    "Total Time" : "2:31.28",
    "Diff." : "+3.73",
    "FIS Points" : "21.74",
    "WC Points" : "0.00"
  }, {
    "Rank" : "16",
    "Bib" : "2",
    "FIS Code" : "55198",
    "Name" : "DORFMEISTER Michaela",
    "Year" : "1973",
    "Nation" : "AUT",
    "Run 1" : "1:15.32",
    "Run 2" : "1:16.03",
    "Total Time" : "2:31.35",
    "Diff." : "+3.80",
    "FIS Points" : "22.15",
    "WC Points" : "0.00"
  }, {
    "Rank" : "17",
    "Bib" : "10",
    "FIS Code" : "106022",
    "Name" : "JANYK Britt",
    "Year" : "1980",
    "Nation" : "CAN",
    "Run 1" : "1:15.08",
    "Run 2" : "1:16.94",
    "Total Time" : "2:32.02",
    "Diff." : "+4.47",
    "FIS Points" : "26.05",
    "WC Points" : "0.00"
  }, {
    "Rank" : "18",
    "Bib" : "24",
    "FIS Code" : "296008",
    "Name" : "MERIGHETTI Daniela",
    "Year" : "1981",
    "Nation" : "ITA",
    "Run 1" : "1:16.27",
    "Run 2" : "1:16.19",
    "Total Time" : "2:32.46",
    "Diff." : "+4.91",
    "FIS Points" : "28.62",
    "WC Points" : "0.00"
  }, {
    "Rank" : "19",
    "Bib" : "26",
    "FIS Code" : "295136",
    "Name" : "CECCARELLI Daniela",
    "Year" : "1975",
    "Nation" : "ITA",
    "Run 1" : "1:16.47",
    "Run 2" : "1:16.13",
    "Total Time" : "2:32.60",
    "Diff." : "+5.05",
    "FIS Points" : "29.43",
    "WC Points" : "0.00"
  }, {
    "Rank" : "20",
    "Bib" : "6",
    "FIS Code" : "385022",
    "Name" : "KOSTELIC Janica",
    "Year" : "1982",
    "Nation" : "CRO",
    "Run 1" : "1:16.67",
    "Run 2" : "1:16.26",
    "Total Time" : "2:32.93",
    "Diff." : "+5.38",
    "FIS Points" : "31.36",
    "WC Points" : "0.00"
  }, {
    "Rank" : "Did not finish 2nd run"
  }, {
    "Rank" : ""
  }, {
    "Rank" : "",
    "Bib" : "22",
    "FIS Code" : "106056",
    "Name" : "SIMARD Genevieve",
    "Year" : "1980",
    "Nation" : "CAN",
    "Run 1" : "",
    "Run 2" : "",
    "Total Time" : "",
    "Diff." : "",
    "FIS Points" : "",
    "WC Points" : "0.00"
  }, {
    "Rank" : "",
    "Bib" : "16",
    "FIS Code" : "55261",
    "Name" : "OBERMOSER Brigitte",
    "Year" : "1976",
    "Nation" : "AUT",
    "Run 1" : "",
    "Run 2" : "",
    "Total Time" : "",
    "Diff." : "",
    "FIS Points" : "",
    "WC Points" : "0.00"
  }, {
    "Rank" : "",
    "Bib" : "14",
    "FIS Code" : "185140",
    "Name" : "POUTIAINEN Tanja",
    "Year" : "1980",
    "Nation" : "FIN",
    "Run 1" : "",
    "Run 2" : "",
    "Total Time" : "",
    "Diff." : "",
    "FIS Points" : "",
    "WC Points" : "0.00"
  }, {
    "Rank" : "",
    "Bib" : "13",
    "FIS Code" : "355002",
    "Name" : "HEEB-BATLINER Birgit",
    "Year" : "1972",
    "Nation" : "LIE",
    "Run 1" : "",
    "Run 2" : "",
    "Total Time" : "",
    "Diff." : "",
    "FIS Points" : "",
    "WC Points" : "0.00"
  }, {
    "Rank" : "",
    "Bib" : "1",
    "FIS Code" : "495065",
    "Name" : "RIENDA CONTRERAS Maria Jose",
    "Year" : "1975",
    "Nation" : "ESP",
    "Run 1" : "",
    "Run 2" : "",
    "Total Time" : "",
    "Diff." : "",
    "FIS Points" : "",
    "WC Points" : "0.00"
  }, {
    "Rank" : "Did not finish 1st run"
  }, {
    "Rank" : ""
  }, {
    "Rank" : "",
    "Bib" : "25",
    "FIS Code" : "505632",
    "Name" : "LINDELL-VIKARBY Jessica",
    "Year" : "1984",
    "Nation" : "SWE",
    "Run 1" : "",
    "Run 2" : "",
    "Total Time" : "",
    "Diff." : "",
    "FIS Points" : "",
    "WC Points" : "0.00"
  }, {
    "Rank" : ""
  } ]
}