{
  "result" : [ {
    "Rank" : "1",
    "Bib" : "",
    "FIS Code" : "-10731",
    "Name" : "PELEN Perrine",
    "Year" : "1960",
    "Nation" : "FRA",
    "Run 1" : "",
    "Run 2" : "",
    "Total Time" : "1:19.00",
    "Diff." : "",
    "FIS Points" : "0.00"
  }, {
    "Rank" : "2",
    "Bib" : "",
    "FIS Code" : "-10269",
    "Name" : "SERRAT Fabienne",
    "Year" : "1956",
    "Nation" : "FRA",
    "Run 1" : "",
    "Run 2" : "",
    "Total Time" : "1:19.01",
    "Diff." : "+0.01",
    "FIS Points" : "0.00"
  }, {
    "Rank" : "3",
    "Bib" : "",
    "FIS Code" : "-10348",
    "Name" : "WENZEL Hanni",
    "Year" : "1956",
    "Nation" : "LIE",
    "Run 1" : "",
    "Run 2" : "",
    "Total Time" : "1:19.76",
    "Diff." : "+0.76",
    "FIS Points" : "0.00"
  }, {
    "Rank" : "4",
    "Bib" : "",
    "FIS Code" : "-10537",
    "Name" : "SOLKNER Lea",
    "Year" : "1958",
    "Nation" : "AUT",
    "Run 1" : "",
    "Run 2" : "",
    "Total Time" : "1:19.80",
    "Diff." : "+0.80",
    "FIS Points" : "0.00"
  }, {
    "Rank" : "5",
    "Bib" : "",
    "FIS Code" : "-10051",
    "Name" : "MOSER-PROELL Annemarie",
    "Year" : "1953",
    "Nation" : "AUT",
    "Run 1" : "",
    "Run 2" : "",
    "Total Time" : "1:19.92",
    "Diff." : "+0.92",
    "FIS Points" : "0.00"
  }, {
    "Rank" : "6",
    "Bib" : "",
    "FIS Code" : "-10392",
    "Name" : "EBERLE Ingrid",
    "Year" : "",
    "Nation" : "AUT",
    "Run 1" : "",
    "Run 2" : "",
    "Total Time" : "1:19.98",
    "Diff." : "+0.98",
    "FIS Points" : "0.00"
  }, {
    "Rank" : "7",
    "Bib" : "",
    "FIS Code" : "-10171",
    "Name" : "NELSON Cindy",
    "Year" : "1955",
    "Nation" : "USA",
    "Run 1" : "",
    "Run 2" : "",
    "Total Time" : "1:19.99",
    "Diff." : "+0.99",
    "FIS Points" : "0.00"
  }, {
    "Rank" : "8",
    "Bib" : "",
    "FIS Code" : "-10675",
    "Name" : "KASERER Monika",
    "Year" : "1952",
    "Nation" : "AUT",
    "Run 1" : "",
    "Run 2" : "",
    "Total Time" : "1:20.11",
    "Diff." : "+1.11",
    "FIS Points" : "0.00"
  }, {
    "Rank" : "9",
    "Bib" : "",
    "FIS Code" : "-10499",
    "Name" : "KREINER Kathy",
    "Year" : "1957",
    "Nation" : "CAN",
    "Run 1" : "",
    "Run 2" : "",
    "Total Time" : "1:20.13",
    "Diff." : "+1.13",
    "FIS Points" : "0.00"
  }, {
    "Rank" : "10",
    "Bib" : "",
    "FIS Code" : "-10581",
    "Name" : "EPPLE Maria",
    "Year" : "1959",
    "Nation" : "BRD",
    "Run 1" : "",
    "Run 2" : "",
    "Total Time" : "1:20.26",
    "Diff." : "+1.26",
    "FIS Points" : "0.00"
  }, {
    "Rank" : ""
  } ]
}