{
  "raceInfo" : {
    "Jury" : {
      "TD FIS" : {
        "name" : "",
        "country" : ""
      },
      "Referee" : {
        "name" : "",
        "country" : ""
      },
      "Chief of Race" : {
        "name" : "",
        "country" : ""
      }
    },
    "Technical Data" : {
      "Start Altitude" : "m.",
      "Finish Altitude" : "m.",
      "Vertical Drop" : "0 m.",
      "Homologation Number" : ""
    }
  },
  "results" : [ {
    "Rank" : "1",
    "Bib" : "",
    "FIS Code" : "-10731",
    "Name" : "PELEN Perrine",
    "Year" : "1960",
    "Nation" : "FRA",
    "Run 1" : "",
    "Run 2" : "",
    "Total Time" : "1:42.58",
    "Diff." : "",
    "FIS Points" : "0.00"
  }, {
    "Rank" : "2",
    "Bib" : "",
    "FIS Code" : "-10175",
    "Name" : "GIORDANI Claudia",
    "Year" : "1955",
    "Nation" : "ITA",
    "Run 1" : "",
    "Run 2" : "",
    "Total Time" : "1:43.19",
    "Diff." : "+0.61",
    "FIS Points" : "0.00"
  }, {
    "Rank" : "3",
    "Bib" : "",
    "FIS Code" : "-10675",
    "Name" : "KASERER Monika",
    "Year" : "1952",
    "Nation" : "AUT",
    "Run 1" : "",
    "Run 2" : "",
    "Total Time" : "1:43.36",
    "Diff." : "+0.78",
    "FIS Points" : "0.00"
  }, {
    "Rank" : "4",
    "Bib" : "",
    "FIS Code" : "-10550",
    "Name" : "MOREROD Lise-Marie",
    "Year" : "1956",
    "Nation" : "SUI",
    "Run 1" : "",
    "Run 2" : "",
    "Total Time" : "1:43.60",
    "Diff." : "+1.02",
    "FIS Points" : "0.00"
  }, {
    "Rank" : "5",
    "Bib" : "",
    "FIS Code" : "-10197",
    "Name" : "DEBERNARD Danielle",
    "Year" : "1954",
    "Nation" : "FRA",
    "Run 1" : "",
    "Run 2" : "",
    "Total Time" : "1:43.62",
    "Diff." : "+1.04",
    "FIS Points" : "0.00"
  }, {
    "Rank" : "6",
    "Bib" : "",
    "FIS Code" : "-10392",
    "Name" : "EBERLE Ingrid",
    "Year" : "",
    "Nation" : "AUT",
    "Run 1" : "",
    "Run 2" : "",
    "Total Time" : "1:43.93",
    "Diff." : "+1.35",
    "FIS Points" : "0.00"
  }, {
    "Rank" : "7",
    "Bib" : "",
    "FIS Code" : "-10150",
    "Name" : "ZECHMEISTER Christa",
    "Year" : "1957",
    "Nation" : "BRD",
    "Run 1" : "",
    "Run 2" : "",
    "Total Time" : "1:44.02",
    "Diff." : "+1.44",
    "FIS Points" : "0.00"
  }, {
    "Rank" : "8",
    "Bib" : "",
    "FIS Code" : "-10001",
    "Name" : "FISHER Abbi",
    "Year" : "1957",
    "Nation" : "USA",
    "Run 1" : "",
    "Run 2" : "",
    "Total Time" : "1:44.12",
    "Diff." : "+1.54",
    "FIS Points" : "0.00"
  }, {
    "Rank" : "9",
    "Bib" : "",
    "FIS Code" : "-10269",
    "Name" : "SERRAT Fabienne",
    "Year" : "1956",
    "Nation" : "FRA",
    "Run 1" : "",
    "Run 2" : "",
    "Total Time" : "1:44.40",
    "Diff." : "+1.82",
    "FIS Points" : "0.00"
  }, {
    "Rank" : "10",
    "Bib" : "",
    "FIS Code" : "-10669",
    "Name" : "BERWEIN Monika",
    "Year" : "",
    "Nation" : "BRD",
    "Run 1" : "",
    "Run 2" : "",
    "Total Time" : "1:44.59",
    "Diff." : "+2.01",
    "FIS Points" : "0.00"
  }, {
    "Rank" : ""
  } ],
  "eventInfo" : {
    "Date" : "05.03.1977",
    "Place" : "Sun Valley, ID",
    "Nation" : "USA",
    "Codex" : "2344",
    "Discipline" : "Slalom",
    "Gender" : "L",
    "Category" : "WC",
    "Comments" : "",
    "Down load" : ""
  }
}