{
  "result" : [ {
    "Rank" : "1",
    "Bib" : "",
    "FIS Code" : "-10341",
    "Name" : "THOENI Gustavo",
    "Year" : "1951",
    "Nation" : "ITA",
    "Run 1" : "",
    "Run 2" : "",
    "Total Time" : "1:44.89",
    "Diff." : "",
    "FIS Points" : "0.00"
  }, {
    "Rank" : "2",
    "Bib" : "",
    "FIS Code" : "-10154",
    "Name" : "NEUREUTHER Christian",
    "Year" : "1949",
    "Nation" : "BRD",
    "Run 1" : "",
    "Run 2" : "",
    "Total Time" : "1:46.56",
    "Diff." : "+1.67",
    "FIS Points" : "0.00"
  }, {
    "Rank" : "3",
    "Bib" : "",
    "FIS Code" : "-10907",
    "Name" : "PALMER Tyler",
    "Year" : "1950",
    "Nation" : "USA",
    "Run 1" : "",
    "Run 2" : "",
    "Total Time" : "1:46.62",
    "Diff." : "+1.73",
    "FIS Points" : "0.00"
  }, {
    "Rank" : "4",
    "Bib" : "",
    "FIS Code" : "-10204",
    "Name" : "ZWILLING David",
    "Year" : "1949",
    "Nation" : "AUT",
    "Run 1" : "",
    "Run 2" : "",
    "Total Time" : "1:46.90",
    "Diff." : "+2.01",
    "FIS Points" : "0.00"
  }, {
    "Rank" : "5",
    "Bib" : "",
    "FIS Code" : "-10374",
    "Name" : "DUVILLARD Henri",
    "Year" : "1947",
    "Nation" : "FRA",
    "Run 1" : "",
    "Run 2" : "",
    "Total Time" : "1:47.05",
    "Diff." : "+2.16",
    "FIS Points" : "0.00"
  }, {
    "Rank" : "6",
    "Bib" : "",
    "FIS Code" : "-10781",
    "Name" : "CHAFFEE Rick",
    "Year" : "",
    "Nation" : "USA",
    "Run 1" : "",
    "Run 2" : "",
    "Total Time" : "1:47.74",
    "Diff." : "+2.85",
    "FIS Points" : "0.00"
  }, {
    "Rank" : "7",
    "Bib" : "",
    "FIS Code" : "-10706",
    "Name" : "TSCHUDI Otto",
    "Year" : "",
    "Nation" : "NOR",
    "Run 1" : "",
    "Run 2" : "",
    "Total Time" : "1:48.19",
    "Diff." : "+3.30",
    "FIS Points" : "0.00"
  }, {
    "Rank" : "8",
    "Bib" : "",
    "FIS Code" : "-10234",
    "Name" : "BRUGGMANN Edmund",
    "Year" : "1943",
    "Nation" : "SUI",
    "Run 1" : "",
    "Run 2" : "",
    "Total Time" : "1:48.31",
    "Diff." : "+3.42",
    "FIS Points" : "0.00"
  }, {
    "Rank" : "9",
    "Bib" : "",
    "FIS Code" : "-10248",
    "Name" : "POULSEN Eric",
    "Year" : "",
    "Nation" : "USA",
    "Run 1" : "",
    "Run 2" : "",
    "Total Time" : "1:48.53",
    "Diff." : "+3.64",
    "FIS Points" : "0.00"
  }, {
    "Rank" : "10",
    "Bib" : "",
    "FIS Code" : "-10633",
    "Name" : "RIEGER Max",
    "Year" : "1946",
    "Nation" : "BRD",
    "Run 1" : "",
    "Run 2" : "",
    "Total Time" : "1:48.62",
    "Diff." : "+3.73",
    "FIS Points" : "0.00"
  }, {
    "Rank" : ""
  } ]
}