{
  "raceInfo" : {
    "Jury" : {
      "TD FIS" : {
        "name" : "",
        "country" : ""
      },
      "Referee" : {
        "name" : "",
        "country" : ""
      },
      "Chief of Race" : {
        "name" : "",
        "country" : ""
      }
    },
    "Technical Data" : {
      "Start Altitude" : "m.",
      "Finish Altitude" : "m.",
      "Vertical Drop" : "0 m.",
      "Course Length" : "m.",
      "Homologation Number" : ""
    }
  },
  "results" : [ {
    "Rank" : "1",
    "Bib" : "",
    "FIS Code" : "190010",
    "Name" : "ALPHAND Luc",
    "Year" : "1965",
    "Nation" : "FRA",
    "Total Time" : "1:15.32",
    "Diff." : "",
    "FIS Points" : "-4.00",
    "WC Points" : "0.00"
  }, {
    "Rank" : "2",
    "Bib" : "",
    "FIS Code" : "50423",
    "Name" : "MAIER Hermann",
    "Year" : "1972",
    "Nation" : "AUT",
    "Total Time" : "1:15.87",
    "Diff." : "+0.55",
    "FIS Points" : "2.86",
    "WC Points" : "0.00"
  }, {
    "Rank" : "3",
    "Bib" : "",
    "FIS Code" : "290398",
    "Name" : "PERATHONER Werner",
    "Year" : "1967",
    "Nation" : "ITA",
    "Total Time" : "1:15.90",
    "Diff." : "+0.58",
    "FIS Points" : "3.24",
    "WC Points" : "0.00"
  }, {
    "Rank" : "4",
    "Bib" : "",
    "FIS Code" : "100465",
    "Name" : "PODIVINSKY Ed",
    "Year" : "1970",
    "Nation" : "CAN",
    "Total Time" : "1:15.96",
    "Diff." : "+0.64",
    "FIS Points" : "3.99",
    "WC Points" : "0.00"
  }, {
    "Rank" : "5",
    "Bib" : "",
    "FIS Code" : "420382",
    "Name" : "AAMODT Kjetil Andre",
    "Year" : "1971",
    "Nation" : "NOR",
    "Total Time" : "1:15.97",
    "Diff." : "+0.65",
    "FIS Points" : "4.11",
    "WC Points" : "0.00"
  }, {
    "Rank" : "6",
    "Bib" : "",
    "FIS Code" : "510478",
    "Name" : "KERNEN Bruno Ii",
    "Year" : "1972",
    "Nation" : "SUI",
    "Total Time" : "1:15.98",
    "Diff." : "+0.66",
    "FIS Points" : "4.24",
    "WC Points" : "0.00"
  }, {
    "Rank" : "7",
    "Bib" : "",
    "FIS Code" : "290466",
    "Name" : "RUNGGALDIER Peter",
    "Year" : "1968",
    "Nation" : "ITA",
    "Total Time" : "1:16.14",
    "Diff." : "+0.82",
    "FIS Points" : "6.23",
    "WC Points" : "0.00"
  }, {
    "Rank" : "8",
    "Bib" : "",
    "FIS Code" : "531040",
    "Name" : "RAHLVES Daron",
    "Year" : "1973",
    "Nation" : "USA",
    "Total Time" : "1:16.16",
    "Diff." : "+0.84",
    "FIS Points" : "6.48",
    "WC Points" : "0.00"
  }, {
    "Rank" : "9",
    "Bib" : "",
    "FIS Code" : "50149",
    "Name" : "STROBL Josef",
    "Year" : "1974",
    "Nation" : "AUT",
    "Total Time" : "1:16.20",
    "Diff." : "+0.88",
    "FIS Points" : "6.98",
    "WC Points" : "0.00"
  }, {
    "Rank" : "10",
    "Bib" : "",
    "FIS Code" : "420182",
    "Name" : "SKAARDAL Atle",
    "Year" : "1966",
    "Nation" : "NOR",
    "Total Time" : "1:16.22",
    "Diff." : "+0.90",
    "FIS Points" : "7.23",
    "WC Points" : "0.00"
  }, {
    "Rank" : "11",
    "Bib" : "",
    "FIS Code" : "480031",
    "Name" : "FILISCHKIN Andrej",
    "Year" : "1975",
    "Nation" : "RUS",
    "Total Time" : "1:16.34",
    "Diff." : "+1.02",
    "FIS Points" : "8.73",
    "WC Points" : "0.00"
  }, {
    "Rank" : "12",
    "Bib" : "",
    "FIS Code" : "420470",
    "Name" : "KJUS Lasse",
    "Year" : "1971",
    "Nation" : "NOR",
    "Total Time" : "1:16.40",
    "Diff." : "+1.08",
    "FIS Points" : "9.48",
    "WC Points" : "0.00"
  }, {
    "Rank" : "12",
    "Bib" : "",
    "FIS Code" : "190096",
    "Name" : "CRETIER Jean-Luc",
    "Year" : "1966",
    "Nation" : "FRA",
    "Total Time" : "1:16.40",
    "Diff." : "+1.08",
    "FIS Points" : "9.48",
    "WC Points" : "0.00"
  }, {
    "Rank" : "14",
    "Bib" : "",
    "FIS Code" : "50127",
    "Name" : "MADER Guenther",
    "Year" : "1964",
    "Nation" : "AUT",
    "Total Time" : "1:16.44",
    "Diff." : "+1.12",
    "FIS Points" : "9.98",
    "WC Points" : "0.00"
  }, {
    "Rank" : "15",
    "Bib" : "",
    "FIS Code" : "50360",
    "Name" : "KNAUSS Hans",
    "Year" : "1971",
    "Nation" : "AUT",
    "Total Time" : "1:16.51",
    "Diff." : "+1.19",
    "FIS Points" : "10.85",
    "WC Points" : "0.00"
  }, {
    "Rank" : "16",
    "Bib" : "",
    "FIS Code" : "190462",
    "Name" : "MELQUIOND Benjamin",
    "Year" : "1975",
    "Nation" : "FRA",
    "Total Time" : "1:16.58",
    "Diff." : "+1.26",
    "FIS Points" : "11.72",
    "WC Points" : "0.00"
  }, {
    "Rank" : "17",
    "Bib" : "",
    "FIS Code" : "50144",
    "Name" : "ORTLIEB Patrick",
    "Year" : "1967",
    "Nation" : "AUT",
    "Total Time" : "1:16.64",
    "Diff." : "+1.32",
    "FIS Points" : "12.47",
    "WC Points" : "0.00"
  }, {
    "Rank" : "18",
    "Bib" : "",
    "FIS Code" : "290255",
    "Name" : "GHEDINA Kristian",
    "Year" : "1969",
    "Nation" : "ITA",
    "Total Time" : "1:16.67",
    "Diff." : "+1.35",
    "FIS Points" : "12.85",
    "WC Points" : "0.00"
  }, {
    "Rank" : "19",
    "Bib" : "",
    "FIS Code" : "510145",
    "Name" : "LOCHER Steve",
    "Year" : "1967",
    "Nation" : "SUI",
    "Total Time" : "1:16.70",
    "Diff." : "+1.38",
    "FIS Points" : "13.22",
    "WC Points" : "0.00"
  }, {
    "Rank" : "19",
    "Bib" : "",
    "FIS Code" : "510035",
    "Name" : "CAVEGN Franco",
    "Year" : "1971",
    "Nation" : "SUI",
    "Total Time" : "1:16.70",
    "Diff." : "+1.38",
    "FIS Points" : "13.22",
    "WC Points" : "0.00"
  }, {
    "Rank" : "21",
    "Bib" : "",
    "FIS Code" : "420830",
    "Name" : "GROENVOLD Audun",
    "Year" : "1976",
    "Nation" : "NOR",
    "Total Time" : "1:16.79",
    "Diff." : "+1.47",
    "FIS Points" : "14.35",
    "WC Points" : "0.00"
  }, {
    "Rank" : "22",
    "Bib" : "",
    "FIS Code" : "510029",
    "Name" : "BESSE William",
    "Year" : "1968",
    "Nation" : "SUI",
    "Total Time" : "1:16.84",
    "Diff." : "+1.52",
    "FIS Points" : "14.97",
    "WC Points" : "0.00"
  }, {
    "Rank" : "23",
    "Bib" : "",
    "FIS Code" : "50124",
    "Name" : "SCHIFFERER Andreas",
    "Year" : "1974",
    "Nation" : "AUT",
    "Total Time" : "1:16.90",
    "Diff." : "+1.58",
    "FIS Points" : "15.72",
    "WC Points" : "0.00"
  }, {
    "Rank" : "24",
    "Bib" : "",
    "FIS Code" : "510001",
    "Name" : "ACCOLA Paul",
    "Year" : "1967",
    "Nation" : "SUI",
    "Total Time" : "1:16.92",
    "Diff." : "+1.60",
    "FIS Points" : "15.97",
    "WC Points" : "0.00"
  }, {
    "Rank" : "24",
    "Bib" : "",
    "FIS Code" : "291116",
    "Name" : "FATTORI Alessandro",
    "Year" : "1973",
    "Nation" : "ITA",
    "Total Time" : "1:16.92",
    "Diff." : "+1.60",
    "FIS Points" : "15.97",
    "WC Points" : "0.00"
  }, {
    "Rank" : "26",
    "Bib" : "",
    "FIS Code" : "50221",
    "Name" : "TRINKL Hannes",
    "Year" : "1968",
    "Nation" : "AUT",
    "Total Time" : "1:16.96",
    "Diff." : "+1.64",
    "FIS Points" : "16.47",
    "WC Points" : "0.00"
  }, {
    "Rank" : "27",
    "Bib" : "",
    "FIS Code" : "200705",
    "Name" : "RAUFFER Max",
    "Year" : "1972",
    "Nation" : "GER",
    "Total Time" : "1:17.08",
    "Diff." : "+1.76",
    "FIS Points" : "17.96",
    "WC Points" : "0.00"
  }, {
    "Rank" : "28",
    "Bib" : "",
    "FIS Code" : "530194",
    "Name" : "KITT A J",
    "Year" : "1968",
    "Nation" : "USA",
    "Total Time" : "1:17.10",
    "Diff." : "+1.78",
    "FIS Points" : "18.21",
    "WC Points" : "0.00"
  }, {
    "Rank" : "28",
    "Bib" : "",
    "FIS Code" : "560013",
    "Name" : "BREZAVSEK Ales",
    "Year" : "1972",
    "Nation" : "SLO",
    "Total Time" : "1:17.10",
    "Diff." : "+1.78",
    "FIS Points" : "18.21",
    "WC Points" : "0.00"
  }, {
    "Rank" : "30",
    "Bib" : "",
    "FIS Code" : "560187",
    "Name" : "PEN Peter",
    "Year" : "1973",
    "Nation" : "SLO",
    "Total Time" : "1:17.15",
    "Diff." : "+1.83",
    "FIS Points" : "18.84",
    "WC Points" : "0.00"
  }, {
    "Rank" : "31",
    "Bib" : "",
    "FIS Code" : "50393",
    "Name" : "WIRTH Patrick",
    "Year" : "1971",
    "Nation" : "AUT",
    "Total Time" : "1:17.18",
    "Diff." : "+1.86",
    "FIS Points" : "19.21",
    "WC Points" : "0.00"
  }, {
    "Rank" : "32",
    "Bib" : "",
    "FIS Code" : "560151",
    "Name" : "KOBLAR Jernej",
    "Year" : "1971",
    "Nation" : "SLO",
    "Total Time" : "1:17.19",
    "Diff." : "+1.87",
    "FIS Points" : "19.34",
    "WC Points" : "0.00"
  }, {
    "Rank" : "32",
    "Bib" : "",
    "FIS Code" : "100744",
    "Name" : "OLDFIELD Graydon",
    "Year" : "1973",
    "Nation" : "CAN",
    "Total Time" : "1:17.19",
    "Diff." : "+1.87",
    "FIS Points" : "19.34",
    "WC Points" : "0.00"
  }, {
    "Rank" : "34",
    "Bib" : "",
    "FIS Code" : "190314",
    "Name" : "SAIONI Christophe",
    "Year" : "1969",
    "Nation" : "FRA",
    "Total Time" : "1:17.21",
    "Diff." : "+1.89",
    "FIS Points" : "19.59",
    "WC Points" : "0.00"
  }, {
    "Rank" : "35",
    "Bib" : "",
    "FIS Code" : "200249",
    "Name" : "STANKALLA Stefan",
    "Year" : "1975",
    "Nation" : "GER",
    "Total Time" : "1:17.28",
    "Diff." : "+1.96",
    "FIS Points" : "20.46",
    "WC Points" : "0.00"
  }, {
    "Rank" : "36",
    "Bib" : "",
    "FIS Code" : "190294",
    "Name" : "MARIN-CUDRAZ Frederic",
    "Year" : "1974",
    "Nation" : "FRA",
    "Total Time" : "1:17.29",
    "Diff." : "+1.97",
    "FIS Points" : "20.59",
    "WC Points" : "0.00"
  }, {
    "Rank" : "36",
    "Bib" : "",
    "FIS Code" : "420681",
    "Name" : "SIVERTSEN Kenneth",
    "Year" : "1973",
    "Nation" : "NOR",
    "Total Time" : "1:17.29",
    "Diff." : "+1.97",
    "FIS Points" : "20.59",
    "WC Points" : "0.00"
  }, {
    "Rank" : "38",
    "Bib" : "",
    "FIS Code" : "420696",
    "Name" : "PAULSEN Lasse",
    "Year" : "1974",
    "Nation" : "NOR",
    "Total Time" : "1:17.33",
    "Diff." : "+2.01",
    "FIS Points" : "21.08",
    "WC Points" : "0.00"
  }, {
    "Rank" : "39",
    "Bib" : "",
    "FIS Code" : "200170",
    "Name" : "KRAUSS Stefan",
    "Year" : "1967",
    "Nation" : "GER",
    "Total Time" : "1:17.43",
    "Diff." : "+2.11",
    "FIS Points" : "22.33",
    "WC Points" : "0.00"
  }, {
    "Rank" : "40",
    "Bib" : "",
    "FIS Code" : "500150",
    "Name" : "JAERBYN Patrik",
    "Year" : "1969",
    "Nation" : "SWE",
    "Total Time" : "1:17.64",
    "Diff." : "+2.32",
    "FIS Points" : "24.95",
    "WC Points" : "0.00"
  }, {
    "Rank" : "41",
    "Bib" : "",
    "FIS Code" : "190270",
    "Name" : "PICCARD Ian",
    "Year" : "1968",
    "Nation" : "FRA",
    "Total Time" : "1:17.66",
    "Diff." : "+2.34",
    "FIS Points" : "25.20",
    "WC Points" : "0.00"
  }, {
    "Rank" : "42",
    "Bib" : "",
    "FIS Code" : "510313",
    "Name" : "LEHMANN Urs",
    "Year" : "1969",
    "Nation" : "SUI",
    "Total Time" : "1:17.83",
    "Diff." : "+2.51",
    "FIS Points" : "27.33",
    "WC Points" : "0.00"
  }, {
    "Rank" : "43",
    "Bib" : "",
    "FIS Code" : "191007",
    "Name" : "PICCARD Jeff",
    "Year" : "1976",
    "Nation" : "FRA",
    "Total Time" : "1:17.87",
    "Diff." : "+2.55",
    "FIS Points" : "27.82",
    "WC Points" : "0.00"
  }, {
    "Rank" : "44",
    "Bib" : "",
    "FIS Code" : "290756",
    "Name" : "SENIGAGLIESI Alberto",
    "Year" : "1970",
    "Nation" : "ITA",
    "Total Time" : "1:17.95",
    "Diff." : "+2.63",
    "FIS Points" : "28.82",
    "WC Points" : "0.00"
  }, {
    "Rank" : "44",
    "Bib" : "",
    "FIS Code" : "50126",
    "Name" : "MAYER Christian",
    "Year" : "1972",
    "Nation" : "AUT",
    "Total Time" : "1:17.95",
    "Diff." : "+2.63",
    "FIS Points" : "28.82",
    "WC Points" : "0.00"
  }, {
    "Rank" : "46",
    "Bib" : "",
    "FIS Code" : "200099",
    "Name" : "BRUNNER Michael",
    "Year" : "1973",
    "Nation" : "GER",
    "Total Time" : "1:18.24",
    "Diff." : "+2.92",
    "FIS Points" : "32.44",
    "WC Points" : "0.00"
  }, {
    "Rank" : "47",
    "Bib" : "",
    "FIS Code" : "180212",
    "Name" : "UOTILA Sami",
    "Year" : "1976",
    "Nation" : "FIN",
    "Total Time" : "1:18.40",
    "Diff." : "+3.08",
    "FIS Points" : "34.44",
    "WC Points" : "0.00"
  }, {
    "Rank" : "48",
    "Bib" : "",
    "FIS Code" : "510051",
    "Name" : "GRUENENFELDER Juerg",
    "Year" : "1974",
    "Nation" : "SUI",
    "Total Time" : "1:18.42",
    "Diff." : "+3.10",
    "FIS Points" : "34.69",
    "WC Points" : "0.00"
  }, {
    "Rank" : "49",
    "Bib" : "",
    "FIS Code" : "510240",
    "Name" : "SULLIGER Marcel",
    "Year" : "1967",
    "Nation" : "SUI",
    "Total Time" : "1:18.52",
    "Diff." : "+3.20",
    "FIS Points" : "35.94",
    "WC Points" : "0.00"
  }, {
    "Rank" : "50",
    "Bib" : "",
    "FIS Code" : "220003",
    "Name" : "BELL Graham",
    "Year" : "1966",
    "Nation" : "GBR",
    "Total Time" : "1:19.09",
    "Diff." : "+3.77",
    "FIS Points" : "43.05",
    "WC Points" : "0.00"
  }, {
    "Rank" : "51",
    "Bib" : "",
    "FIS Code" : "270016",
    "Name" : "SCHWARZACHER-JOYCE Paul Patrick",
    "Year" : "1972",
    "Nation" : "IRL",
    "Total Time" : "1:24.16",
    "Diff." : "+8.84",
    "FIS Points" : "106.32",
    "WC Points" : "0.00"
  }, {
    "Rank" : "Did not start 1st run"
  }, {
    "Rank" : ""
  }, {
    "Rank" : "",
    "Bib" : "",
    "FIS Code" : "680002",
    "Name" : "DJIDJISHVILI Zurab",
    "Year" : "1973",
    "Nation" : "GEO",
    "Total Time" : "",
    "Diff." : "",
    "FIS Points" : "",
    "WC Points" : "0.00"
  }, {
    "Rank" : "",
    "Bib" : "",
    "FIS Code" : "500423",
    "Name" : "BRUGGE Jesper",
    "Year" : "1975",
    "Nation" : "SWE",
    "Total Time" : "",
    "Diff." : "",
    "FIS Points" : "",
    "WC Points" : "0.00"
  }, {
    "Rank" : "Did not finish 1st run"
  }, {
    "Rank" : ""
  }, {
    "Rank" : "",
    "Bib" : "",
    "FIS Code" : "290705",
    "Name" : "HOLZER Patrick",
    "Year" : "1970",
    "Nation" : "ITA",
    "Total Time" : "",
    "Diff." : "",
    "FIS Points" : "",
    "WC Points" : "0.00"
  }, {
    "Rank" : "",
    "Bib" : "",
    "FIS Code" : "200008",
    "Name" : "BARNERSSOI Tobias",
    "Year" : "1969",
    "Nation" : "GER",
    "Total Time" : "",
    "Diff." : "",
    "FIS Points" : "",
    "WC Points" : "0.00"
  }, {
    "Rank" : "",
    "Bib" : "",
    "FIS Code" : "420556",
    "Name" : "STRAND NILSEN Harald Chr.",
    "Year" : "1971",
    "Nation" : "NOR",
    "Total Time" : "",
    "Diff." : "",
    "FIS Points" : "",
    "WC Points" : "0.00"
  }, {
    "Rank" : "",
    "Bib" : "",
    "FIS Code" : "180064",
    "Name" : "LESKINEN Janne",
    "Year" : "1971",
    "Nation" : "FIN",
    "Total Time" : "",
    "Diff." : "",
    "FIS Points" : "",
    "WC Points" : "0.00"
  }, {
    "Rank" : "",
    "Bib" : "",
    "FIS Code" : "20003",
    "Name" : "LOPEZ Santi",
    "Year" : "1975",
    "Nation" : "AND",
    "Total Time" : "",
    "Diff." : "",
    "FIS Points" : "",
    "WC Points" : "0.00"
  }, {
    "Rank" : "",
    "Bib" : "",
    "FIS Code" : "500139",
    "Name" : "NYBERG Fredrik",
    "Year" : "1969",
    "Nation" : "SWE",
    "Total Time" : "",
    "Diff." : "",
    "FIS Points" : "",
    "WC Points" : "0.00"
  }, {
    "Rank" : "",
    "Bib" : "",
    "FIS Code" : "480010",
    "Name" : "PRIHODCHENKO Dmitrij",
    "Year" : "1973",
    "Nation" : "RUS",
    "Total Time" : "",
    "Diff." : "",
    "FIS Points" : "",
    "WC Points" : "0.00"
  }, {
    "Rank" : "",
    "Bib" : "",
    "FIS Code" : "530391",
    "Name" : "ROSENER Jason",
    "Year" : "1975",
    "Nation" : "USA",
    "Total Time" : "",
    "Diff." : "",
    "FIS Points" : "",
    "WC Points" : "0.00"
  }, {
    "Rank" : "",
    "Bib" : "",
    "FIS Code" : "510504",
    "Name" : "RUPP Heinrich",
    "Year" : "1972",
    "Nation" : "SUI",
    "Total Time" : "",
    "Diff." : "",
    "FIS Points" : "",
    "WC Points" : "0.00"
  }, {
    "Rank" : "",
    "Bib" : "",
    "FIS Code" : "290117",
    "Name" : "CATTANEO Luca",
    "Year" : "1972",
    "Nation" : "ITA",
    "Total Time" : "",
    "Diff." : "",
    "FIS Points" : "",
    "WC Points" : "0.00"
  }, {
    "Rank" : "",
    "Bib" : "",
    "FIS Code" : "531018",
    "Name" : "CRIST Zachary",
    "Year" : "1973",
    "Nation" : "USA",
    "Total Time" : "",
    "Diff." : "",
    "FIS Points" : "",
    "WC Points" : "0.00"
  }, {
    "Rank" : "",
    "Bib" : "",
    "FIS Code" : "200130",
    "Name" : "DEISSENBOECK Christian",
    "Year" : "1973",
    "Nation" : "GER",
    "Total Time" : "",
    "Diff." : "",
    "FIS Points" : "",
    "WC Points" : "0.00"
  }, {
    "Rank" : "",
    "Bib" : "",
    "FIS Code" : "530240",
    "Name" : "FLEISCHER Chad",
    "Year" : "1972",
    "Nation" : "USA",
    "Total Time" : "",
    "Diff." : "",
    "FIS Points" : "",
    "WC Points" : "0.00"
  }, {
    "Rank" : "",
    "Bib" : "",
    "FIS Code" : "190945",
    "Name" : "FOURNIER Sebastien",
    "Year" : "1976",
    "Nation" : "FRA",
    "Total Time" : "",
    "Diff." : "",
    "FIS Points" : "",
    "WC Points" : "0.00"
  }, {
    "Rank" : "",
    "Bib" : "",
    "FIS Code" : "290489",
    "Name" : "SELETTO Erik",
    "Year" : "1975",
    "Nation" : "ITA",
    "Total Time" : "",
    "Diff." : "",
    "FIS Points" : "",
    "WC Points" : "0.00"
  }, {
    "Rank" : "",
    "Bib" : "",
    "FIS Code" : "50182",
    "Name" : "STROBL Fritz",
    "Year" : "1972",
    "Nation" : "AUT",
    "Total Time" : "",
    "Diff." : "",
    "FIS Points" : "",
    "WC Points" : "0.00"
  }, {
    "Rank" : "",
    "Bib" : "",
    "FIS Code" : "290573",
    "Name" : "VITALINI Pietro",
    "Year" : "1967",
    "Nation" : "ITA",
    "Total Time" : "",
    "Diff." : "",
    "FIS Points" : "",
    "WC Points" : "0.00"
  }, {
    "Rank" : "",
    "Bib" : "",
    "FIS Code" : "350031",
    "Name" : "VOGT Achim",
    "Year" : "1970",
    "Nation" : "LIE",
    "Total Time" : "",
    "Diff." : "",
    "FIS Points" : "",
    "WC Points" : "0.00"
  }, {
    "Rank" : "",
    "Bib" : "",
    "FIS Code" : "531030",
    "Name" : "MAKAR Michael",
    "Year" : "1973",
    "Nation" : "USA",
    "Total Time" : "",
    "Diff." : "",
    "FIS Points" : "",
    "WC Points" : "0.00"
  }, {
    "Rank" : "",
    "Bib" : "",
    "FIS Code" : "100354",
    "Name" : "MULLEN Cary",
    "Year" : "1969",
    "Nation" : "CAN",
    "Total Time" : "",
    "Diff." : "",
    "FIS Points" : "",
    "WC Points" : "0.00"
  }, {
    "Rank" : ""
  } ],
  "eventInfo" : {
    "Date" : "21.02.1997",
    "Place" : "Garmisch-Partenkirchen",
    "Nation" : "GER",
    "Codex" : "0110",
    "Discipline" : "Super G",
    "Gender" : "M",
    "Category" : "WC",
    "Comments" : "",
    "Down load" : ""
  }
}