{
  "result" : [ {
    "Rank" : "1",
    "Bib" : "",
    "FIS Code" : "55097",
    "Name" : "WACHTER Anita",
    "Year" : "1967",
    "Nation" : "AUT",
    "Run 1" : "",
    "Run 2" : "",
    "Total Time" : "1:39.40",
    "Diff." : "",
    "FIS Points" : "0.00"
  }, {
    "Rank" : "2",
    "Bib" : "",
    "FIS Code" : "55044",
    "Name" : "LADSTAETTER Ida",
    "Year" : "1965",
    "Nation" : "AUT",
    "Run 1" : "",
    "Run 2" : "",
    "Total Time" : "1:39.48",
    "Diff." : "+0.08",
    "FIS Points" : "0.00"
  }, {
    "Rank" : "3",
    "Bib" : "",
    "FIS Code" : "55048",
    "Name" : "MAIER Ulrike",
    "Year" : "1967",
    "Nation" : "AUT",
    "Run 1" : "",
    "Run 2" : "",
    "Total Time" : "1:39.53",
    "Diff." : "+0.13",
    "FIS Points" : "0.00"
  }, {
    "Rank" : "4",
    "Bib" : "",
    "FIS Code" : "505039",
    "Name" : "NILSSON Camilla",
    "Year" : "1967",
    "Nation" : "SWE",
    "Run 1" : "",
    "Run 2" : "",
    "Total Time" : "1:39.61",
    "Diff." : "+0.21",
    "FIS Points" : "0.00"
  }, {
    "Rank" : "5",
    "Bib" : "",
    "FIS Code" : "195041",
    "Name" : "CHAUVET Patricia",
    "Year" : "1967",
    "Nation" : "FRA",
    "Run 1" : "",
    "Run 2" : "",
    "Total Time" : "1:39.69",
    "Diff." : "+0.29",
    "FIS Points" : "0.00"
  }, {
    "Rank" : "6",
    "Bib" : "",
    "FIS Code" : "55084",
    "Name" : "STROBL Claudia",
    "Year" : "1965",
    "Nation" : "AUT",
    "Run 1" : "",
    "Run 2" : "",
    "Total Time" : "1:39.85",
    "Diff." : "+0.45",
    "FIS Points" : "0.00"
  }, {
    "Rank" : "7",
    "Bib" : "",
    "FIS Code" : "-10667",
    "Name" : "AIJA Monika",
    "Year" : "",
    "Nation" : "SWE",
    "Run 1" : "",
    "Run 2" : "",
    "Total Time" : "1:41.16",
    "Diff." : "+1.76",
    "FIS Points" : "0.00"
  }, {
    "Rank" : "8",
    "Bib" : "",
    "FIS Code" : "205045",
    "Name" : "GERSCH Anette",
    "Year" : "1966",
    "Nation" : "BRD",
    "Run 1" : "",
    "Run 2" : "",
    "Total Time" : "1:41.30",
    "Diff." : "+1.90",
    "FIS Points" : "0.00"
  }, {
    "Rank" : "9",
    "Bib" : "",
    "FIS Code" : "55024",
    "Name" : "GAPP Heidi",
    "Year" : "1966",
    "Nation" : "AUT",
    "Run 1" : "",
    "Run 2" : "",
    "Total Time" : "1:41.35",
    "Diff." : "+1.95",
    "FIS Points" : "0.00"
  }, {
    "Rank" : "10",
    "Bib" : "",
    "FIS Code" : "315007",
    "Name" : "DEZMAN Mojca",
    "Year" : "1967",
    "Nation" : "JUG",
    "Run 1" : "",
    "Run 2" : "",
    "Total Time" : "1:41.50",
    "Diff." : "+2.10",
    "FIS Points" : "0.00"
  }, {
    "Rank" : "11",
    "Bib" : "",
    "FIS Code" : "515049",
    "Name" : "GADIENT Brigitte",
    "Year" : "1963",
    "Nation" : "SUI",
    "Run 1" : "",
    "Run 2" : "",
    "Total Time" : "1:41.83",
    "Diff." : "+2.43",
    "FIS Points" : "0.00"
  }, {
    "Rank" : "12",
    "Bib" : "",
    "FIS Code" : "705018",
    "Name" : "MEDZIHRADSKA Lucia",
    "Year" : "1968",
    "Nation" : "SVK",
    "Run 1" : "",
    "Run 2" : "",
    "Total Time" : "1:42.05",
    "Diff." : "+2.65",
    "FIS Points" : "0.00"
  }, {
    "Rank" : "13",
    "Bib" : "",
    "FIS Code" : "225002",
    "Name" : "BECK Lesley",
    "Year" : "1964",
    "Nation" : "GBR",
    "Run 1" : "",
    "Run 2" : "",
    "Total Time" : "1:42.14",
    "Diff." : "+2.74",
    "FIS Points" : "0.00"
  }, {
    "Rank" : "14",
    "Bib" : "",
    "FIS Code" : "-10908",
    "Name" : "CARLSSON Ulla",
    "Year" : "1965",
    "Nation" : "SWE",
    "Run 1" : "",
    "Run 2" : "",
    "Total Time" : "1:42.35",
    "Diff." : "+2.95",
    "FIS Points" : "0.00"
  }, {
    "Rank" : "15",
    "Bib" : "",
    "FIS Code" : "535221",
    "Name" : "VOELKER Heidi",
    "Year" : "1969",
    "Nation" : "USA",
    "Run 1" : "",
    "Run 2" : "",
    "Total Time" : "1:42.49",
    "Diff." : "+3.09",
    "FIS Points" : "0.00"
  }, {
    "Rank" : ""
  } ]
}